Workbook

Sheet Formeyannis
G1: Si pas hawkish
A2: Actif | B2: Classe | C2: (exemple) | D2: Position | E2: Poids | F2: AVANT | G2: FED | H2: (%)4 | I2: Product name
A3: SPY | B3: Actions | C3: SPY ou ETF | D3: ETF | E3: Long | F3: 20 | G3: 35 | H3: Risk-on | I3: SPDR S&P 500 ETF Trust / SPY/ ESD | J3: Maybe buy 1 options SPY with expiration date at Month +1
A4: GLD | B4: Or | C4: ETF | D4: Long | F4: 20 | G4: 25 | H4: réels | I4: SPDR Gold Shares | J4: GLD (SPDR Gold Shares | N4: If fed dovish buy options on GLD
A5: CHF | B5: FX | C5: USD/CHF | D5: (short) | E5: Short fx | F5: 25 | G5: 20 | H5: devise | I5: USDCHF
A6: TLT | B6: Taux | C6: TLT (Us treasuries) | D6: ETF ou tx | E6: Long | F6: 20 | G6: 15 | H6: mistake | I6: iShares 20+ Year Treasury Bond ETF | J6: Scénario | K6: SPY | L6: GOLD | M6: USD/CHF | N6: TLT
A7: Silver | B7: Silver | C7: ETF | E7: LONG | F7: 5 | I7: BlackRock Institutional Trust Company N.A. - iShares Silver Trust | J7: Hawkish | K7: 0.35 | L7: 0.25 | M7: 0.25 | N7: 0.15
I8: SLV | J8: Dovish | K8: 0.4 | L8: 0.15 | M8: 0.15 | N8: 0.3
A9: SPY | B9: Options | C9: Options | D9: PUT | E9: Long | F9: Prendre avant
K10: Placement sur 2mois
J11: Short-term corp bond ETF | M11: iShares Short-Term Corporate Bond ETF
J12: IGSB
J13: 1‑2 %
C15: Short USDJPY?? High lvl actually | I15: =250000 -> 250000
I16: =I15-13000 -> 237000 | J16: Build a python code for EQUITIES for jade and others with long short momentum value on 5 best and 5 worst equities of sp500. Each month we buy hold and sell at the end
C17: BTC ETH market neutral strategy | I17: =I15*20% -> 50000
C18: for 1 on short ETH i put 1,33 on LONG BTC | F18: Market neutral bcause 0,85-0,95 correlation | I18: =I15*20% -> 50000
C19: 3,75% LONG BTC | D19: 1,25 Short ETH
J20: - Strike : OTM à ~5–7% sous le prix spot actuel voir -10% otm
J21: - Taille : couvrir ~10–20% de la valeur SPY (ex. protéger 10–20% du portefeuille) selon budget prime.
C22: - Après la FED : réévalue corrélations ; si dovish, augmente TLT/SPY ; si hawkish, réduis SPY et augmente cash/liquidité.

Sheet Our strategy
A1: Asset classes | B1: Risk | C1: Risk ($) | D1: Risk per trade | E1: Risk per trade ($) | F1: Duration / Maturity (we'll see)
A2: Equities | B2: 0.3 | C2: ='Trading Contest rules'!$B$2*'Our strategy'!B2 -> 300000 | D2: 0.15 | E2: =C2*D2 -> 45000
A3: ETF | B3: 0.3 | C3: ='Trading Contest rules'!$B$2*'Our strategy'!B3 -> 300000 | D3: 0.15 | E3: =C3*D3 -> 45000
A4: Swap | B4: 0.2 | C4: ='Trading Contest rules'!$B$2*'Our strategy'!B4 -> 200000 | D4: 0.15 | E4: =C4*D4 -> 30000
A5: Bonds | B5: 0.2 | C5: ='Trading Contest rules'!$B$2*'Our strategy'!B5 -> 200000 | D5: 0.15 | E5: =C5*D5 -> 30000
A6: Forwards | B6: 0.2 | C6: ='Trading Contest rules'!$B$2*'Our strategy'!B6 -> 200000 | D6: 0.15 | E6: =C6*D6 -> 30000
A7: Futures | B7: 0.2 | C7: ='Trading Contest rules'!$B$2*'Our strategy'!B7 -> 200000 | D7: 0.15 | E7: =C7*D7 -> 30000
A8: Repo | B8: 0.2 | C8: ='Trading Contest rules'!$B$2*'Our strategy'!B8 -> 200000 | D8: 0.15 | E8: =C8*D8 -> 30000
A9: Options / Options Spread | B9: 0.2 | C9: ='Trading Contest rules'!$B$2*'Our strategy'!B9 -> 200000 | D9: 0.15 | E9: =C9*D9 -> 30000
A10: Commodities (Through Other asset) | B10: 0.2 | C10: ='Trading Contest rules'!$B$2*'Our strategy'!B10 -> 200000 | D10: 0.15 | E10: =C10*D10 -> 30000
A11: FX | B11: 0.2 | C11: ='Trading Contest rules'!$B$2*'Our strategy'!B11 -> 200000 | D11: 0.15 | E11: =C11*D11 -> 30000
A12: Crypto | B12: 0.05 | C12: ='Trading Contest rules'!$B$2*'Our strategy'!B12 -> 50000 | D12: 0.15 | E12: =7500 -> 7500
A13: Mutuals Funds | B13: 0.05 | C13: ='Trading Contest rules'!$B$2*'Our strategy'!B13 -> 50000 | D13: 0.15 | E13: =C13*D13 -> 7500
H19: Target ROI
H20: 1300000
H21: =(H20/'Trading Contest rules'!B2)-1 -> 0.3

Sheet Trading Contest rules
A1: Base currency | B1: EUR
A2: Initial cash balance | B2: 1000000
A3: interest earn on cash | B3: 0
A4: Interest charge on borrowed funds | B4: 0.03
A6: Minimum stock price for buying | B6: 1
A7: Minimum stock price for selling | B7: 3
A8: Margin trading allowed | B8: Yes
A9: Shot selling allowed | B9: Yes
A10: Maximum leverage | B10: 100% of initial portfolio value
A11: Position limit on a single security | B11: 25% of portfolio value
A13: Orders filled up to | B13: 200% of daily trading volume
A14: Commission | B14: 0.001

Sheet Mutual Fund
A1: Symbol | B1: Company / Fund
A2: 00ACLMX | B2: American Century Capital Portfolios Inc - American
A3: A | B3: Vanguard Scottsdale Funds - Vanguard ST Corporate
A4: AAA | B4: DWS Alternative Asset Allocation Plus Fund CI A
A5: AAAAX | B5: DWS ALTN Asset Alloc Plus (A)
A6: AAACX | B6: A3 Alternative Credit Fund
A7: AAADX | B7: Alpine Accelerating Dividend Fund
A8: AAAEX | B8: AllianzGI Health Sciences Fund
A9: AAAFX | B9: American Century Asset Allocation Portfolios Inc
A10: AAAGX | B10: Thrivent Large Cap Growth Fund
A11: AAAHX | B11: American Century Asset Allocation Portfolios Inc
A12: BCFGX | B12: Bryce Capital Growth Fund
... A102: ADR | B102: Dreyfus Satellite Alpha Fund

Sheet Trading_Journal
A1: Trade ID | B1: Trader | C1: Trade date | D1: Type | E1: Trading Session | F1: Instrument | G1: Underlying asset | H1: Asset Class | I1: Option direction | J1: Direction | K1: Price paid | L1: Qty | M1: Amount($) | N1: Stop Loss Set | O1: Take Profit Set | P1: Commission + Fees | Q1: Curr./Exch | R1: Amount(€) | S1: Risk (€) | T1: % Portfolio Risked | U1: Position Limit % | V1: Setup Type | W1: Market Context | X1: Catalyst / Trigger | Y1: Hypothesis | Z1: Expected Duration | AA1: Emotional State at Entry | AB1: Emotional State at Exit | AC1: What Worked | AD1: What Didn’t | AE1: What to Improve Next Time | AF1: Major Economic News / Releases | AG1: Inter-Market Observations | AH1: Unexpected Events Affecting Trade | AI1: Strategy | AJ1: Time Frame
A2: 1 | B2: Yannis Khalfi | C2: 46044.8 | D2: Market | E2: Asia | F2: Forex | G2: EUR/USD | H2: FX | J2: Buy
A3: 2 | B3: Yannis Khalfi | C3: 46044.802 | D3: Market | E3: Asia | F3: Forex | G3: EUR/USD | H3: FX | J3: Sell
A4: 3 | B4: Yannis Khalfi | C4: 46048.295 | D4: Market | E4: Asia | F4: Cryptos | G4: BTC | H4: Crypto | J4: Buy | K4: 87701.2 | L4: 0.1709 | M4: -12600.58 | N4: 65000 | O4: 97000(minimum) | P4: =-10 -> -10 | Q4: 0.8407 | R4: =M4*Q4 -> -10593.308 | S4: =ABS(R4) -> 10593.308 | T4: =S4/1000000 -> 0.010593308 | U4: 10-12% | V4: Safe Haven | W4: Tense geopolitical context involving Trump and Greenland. Three days ahead of the Fed rate decision. BTC at a key technical level. I expect investor inflows if conditions deteriorate further. | X4: Risky Safe haven inflows | Y4: BTC come back some strength | Z4: Short term swing | AA4: Confident | AB4: Calm | AF4: FED Rates in 3 days. Wednesday 28/01/2026 | AI4: Macro on Crypto | AJ4: D
A5: 4 | B5: Yannis Khalfi | C5: 46048.648 | D5: Market | E5: NY | F5: ETF | G5: SPY | H5: ETF | J5: Buy | K5: 690.93 | L5: 65 | M5: =-37756.37 -> -37756.37 | N5: 650.4 | P5: =-10 -> -10 | Q5: 0.8407 | R5: =M5*Q5 -> -31741.78 | S5: =ABS(R5) -> 31741.78 | T5: =S5/1000000 -> 0.03174178 | U5: 0.08 | V5: Passive income | W5: High volatility, fed rates announcement soon. Stocks can go high if rates are getting lowered | X5: Good ROI on this benchmark | Y5: USD weakness - More exportation More money for US STOCKS | Z5: Short term swing | AA5: Confident | AF5: FED Rates in 3 days. Wednesday 28/01/2026 | AI5: Macro on Stocks | AJ5: D
A6: 5 | B6: Jade Sancho | C6: 46049.646 | D6: Limit | E6: NY | F6: Option | G6: NVDA | H6: Call | I6: Long | J6: Buy | K6: 3.4 | L6: 100 | M6: =-28624.35 -> -28624.35 | O6: 10% profit | P6: -1 | Q6: 0.84189 | R6: =M6*Q6 -> -24098.554 | S6: =ABS(R6) -> 24098.554 | T6: =S6/1000000 -> 0.024098554 | V6: moderated risk | W6: Given heightened macroeconomic uncertainty around Federal Reserve communication, we implemented a short-term ATM straddle on NVIDIA, a high-beta technology stock, to capture potential volatility expansion. | X6: Risky Safe haven inflows | Y6: If big shift in NASDAQ after fed news, NVDA will shift accordingly | Z6: Short term swing | AA6: Depends on Fed news | AB6: Could have waited longer, but no loss occured | AF6: FED Rates in 3 days. Wednesday 28/01/2026 | AG6: The sharp decline in Nvidia followed earnings despite strong fundamentals, mainly due to extreme pre-earnings expectations, profit-taking, and options-driven hedging flows amplifying the downside move | AI6: Macro on options | AJ6: W
A7: 6 | B7: Jade Sancho | C7: 46049.646 | D7: Limit | E7: NY | F7: Option | G7: NVDA | H7: Put | I7: Long | J7: Buy | K7: 6.7 | L7: 100 | M7: -56406.8 | O7: 10% profit | P7: -1 | Q7: 0.84189 | R7: =M7*Q7 -> -47488.321 | S7: =ABS(R7) -> 47488.321 | T7: =S7/1000000 -> 0.047488321 | V7: moderated risk | W7: Straddle has worked, Nvidia share price moved down a lot and we have a profit on the put vs the call. is is time to close the position | X7: Risky Safe haven inflows | Y7: If big shift in NASDAQ after fed news, NVDA will shift accordingly | Z7: Short term swing | AA7: Depends on Fed news | AB7: Could have waited longer, but no loss occured | AF7: FED Rates in 3 days. Wednesday 28/01/2026 | AI7: Macro on options | AJ7: W
A8: 7 | B8: Wang Jialei | C8: 46050.008 | D8: Market | E8: Asia | F8: Forex | G8: EUR/USD | H8: FX | J8: Buy | K8: 1.20324 | L8: 42000 | M8: =-(L8*K8)*Q8 -> -42545.82 | N8: 1.1448 | O8: 1.26916 | P8: -1 | Q8: 0.84189 | R8: =M8*Q8 -> -35818.901 | S8: 0 | T8: =S8/1000000 -> 0 | U8: 0.06
A9: 8 | B9: Wang Jialei | C9: 46050.009 | D9: Market | E9: Asia | F9: Forex | G9: GBP/USD | H9: FX | J9: Buy | K9: 1.38352 | L9: 34000 | M9: =-(L9*K9)*Q9 -> -39602.236 | N9: 1.30228 | O9: 1.45399 | P9: -1 | Q9: 0.84189 | R9: =M9*Q9 -> -33340.727 | S9: 0 | T9: =S9/1000000 -> 0 | U9: 0.06
A10: 9 | B10: Yannis Khalfi | C10: 46051.646 | D10: Market | E10: NY | F10: Commodity | G10: Silver | H10: Commodity | J10: Buy | K10: 121.479 | L10: 300 | M10: -30472.09 | O10: Looking for a 10% profit | P10: -1 | Q10: 0.83614 | R10: =M10*Q10 -> -25478.933 | S10: =ABS(R10) -> 25478.933 | T10: =S10/1000000 -> 0.025478933 | U10: 30 | V10: Safe haven | W10: Rising gold prices due to geopolitical tensions and Trump announcement. Silver is supposed to follow | X10: Safe haven inflows | Y10: Gold rally continues on macro risk - Silver will follow | Z10: Short term swing | AA10: Confident but a bit stressed because it's overexpended right now | AB10: Mitigated | AF10: FED didn't moved rate yesterday, but TRUMP confirmed that the dollar is in perfect condition and it's lvl of price is perfect. He can do "YOYO" as he said. He wants dollar to be more weak | AG10: USD weakness supported gold | AI10: Global macro | AJ10: D
A11: 10 | B11: Yannis Khalfi | C11: 46052.646 | D11: Market | E11: NY | F11: Commodity | G11: GOLD | H11: Commodity | J11: Buy | K11: 5551.5 | L11: 7 | M11: -32492.87 | O11: Looking for a 10% profit | P11: -1 | Q11: 0.83614 | R11: =M11*Q11 -> -27168.588 | S11: =ABS(R11) -> 27168.588 | T11: =S11/1000000 -> 0.027168588 | U11: 30 | V11: Safe haven | W11: Rising gold prices due to geopolitical tensions and Trump announcement | X11: Safe haven inflows | Y11: Gold rally continues on macro risk | Z11: Short term swing | AA11: Confident but a bit stressed because it's overexpended right now | AB11: Mitigated | AF11: FED didn't moved rate yesterday, but TRUMP confirmed that the dollar is in perfect condition and it's lvl of price is perfect. He can do "YOYO" as he said. He wants dollar to be more weak | AG11: USD weakness supported gold | AI11: Global macro | AJ11: D
A12: 11 | B12: Jade Sancho | C12: 46056.705 | D12: Limit | E12: NY | F12: Option | G12: NVDA | H12: Call | I12: Long | J12: Sell | K12: 0.56 | L12: -100 | M12: 4748.14 | P12: -1 | Q12: 0.84788 | R12: =M12*Q12 -> 4025.8529 | S12: =ABS(R12) -> 4025.8529 | T12: =S12/1000000 -> 0.0040258529
A13: 12 | B13: Jade Sancho | C13: 46056.705 | D13: Limit | E13: NY | F13: Option | G13: NVDA | H13: Put | I13: Long | J13: Sell | K13: 9.71 | L13: -100 | M13: 82329.3 | P13: -1 | Q13: 0.84788 | R13: =M13*Q13 -> 69805.367 | S13: =ABS(R13) -> 69805.367 | T13: =S13/1000000 -> 0.069805367
A14: 13 | B14: Yannis Khalfi | C14: 46058.847 | D14: Market | E14: NY | F14: Cryptos | G14: BTC | H14: Crypto | J14: Sell | K14: 66137.21 | L14: -0.1709 | M14: 9572.93 | P14: -1 | Q14: 0.84695 | R14: =M14*Q14 -> 8107.7931 | S14: =ABS(R14) -> 8107.7931 | T14: =S14/1000000 -> 0.0081077931
A15: 14 | B15: Wanchun Cui | C15: 46059.746 | D15: Market | E15: NY | F15: Fixed Income | G15: T-BOND 3.125% 15/05/2048 | H15: Bond | J15: Buy | K15: 755.21622 | L15: 1 | M15: -647.2 | O15: Looking for a 10% profit | P15: -1 | Q15: 0.84917 | R15: =M15*Q15 -> -549.58282 | S15: =ABS(R15) -> 549.58282 | T15: =S15/1000000 -> 0.00054958282 | U15: 15 | V15: Macro / Duration Trade | W15: Late-cycle, slowing growth, long-end yields elevated | X15: Expected Fed pivot / recession risk / risk-off flows | Y15: Long-end US yields will decline, driving price appreciation via duration and convexity | Z15: middle term | AA15: Calm / Conviction-based | AB15: N/A | AI15: Global macro | AJ15: 5m
A16: 15 | B16: Jade Sancho | C16: 46059.751 | D16: Limit | E16: NY | F16: Option | G16: Microsoft | H16: Call | I16: Long | J16: Buy | K16: 7.75 | L16: 50 | M16: -32905.35 | O16: Looking for 20% profit | P16: -1 | Q16: 0.84917 | R16: =M16*Q16 -> -27942.236 | S16: =ABS(R16) -> 27942.236 | T16: =S16/1000000 -> 0.027942236 | V16: safe Haven | W16: Microsoft just went down 20% due to technological gap, time to invest before it goes up | X16: Safe haven inflows | Y16: Invest in a call as we hope for a increase in Microsoft stock price as there was a sharp decline previously | Z16: Short term swing | AA16: Calm / Conviction-based | AB16: confident | AI16: Macro on options | AJ16: 2D
A17: 16 | B17: Wanchun Cui | C17: 46059.753 | D17: Market | E17: NY | F17: Fixed Income | G17: T-BOND 3.125% 15/05/2048 | H17: Bond | J17: Buy | K17: 755.21622 | L17: 45 | M17: =-29123.83 -> -29123.83 | O17: Looking for a 10% profit | P17: -1 | Q17: 0.84917 | R17: =M17*Q17 -> -24731.083 | S17: =ABS(R17) -> 24731.083 | T17: =S17/1000000 -> 0.024731083 | U17: 15 | V17: Macro / Duration Trade | W17: Late-cycle, slowing growth, long-end yields elevated | X17: Expected Fed pivot / recession risk / risk-off flows | Y17: Long-end US yields will decline, driving price appreciation via duration and convexity | Z17: middle term | AA17: Calm / Conviction-based | AB17: N/A | AI17: Global macro | AJ17: 5m
A18: 17 | B18: Wanchun Cui | C18: 46060.125 | D18: Market | E18: Asia | F18: Fixed Income | G18: BUND 1.250% 15-Nov-2048 | H18: Bond | J18: Buy | K18: 660.46 | L18: 22 | M18: -14660.46 | O18: Looking for a 10% profit | P18: -1 | Q18: 1 | R18: =M18*Q18 -> -14660.46 | S18: =ABS(R18) -> 14660.46 | T18: =S18/1000000 -> 0.01466046 | U18: 15 | V18: Macro / Duration Trade | W18: Late-cycle, slowing growth, long-end yields elevated | X18: Expected Fed pivot / recession risk / risk-off flows | Y18: Long-end US yields will decline, driving price appreciation via duration and convexity | Z18: middle term | AA18: Calm / Conviction-based | AB18: N/A | AI18: Global macro | AJ18: 5m
A19: 18 | B19: Wanchun Cui | C19: 46062.385 | D19: Market | E19: London | F19: Fixed Income | G19: BTP 3.100% 03-Jan-2040 | H19: Bond | J19: Buy | K19: 926.261 | L19: 15 | M19: -14096.48 | O19: According to Bond strategy | P19: -1 | Q19: 1 | R19: =M19*Q19 -> -14096.48 | S19: =ABS(R19) -> 14096.48 | T19: =S19/1000000 -> 0.01409648 | Y19: BTP 2040 LONG to express ECB easing and Italy spread compression. High duration and clean rates/spread beta with manageable volatility over 2-month horizon. | AI19: Bond strategy
A20: 19 | B20: Wanchun Cui | C20: 46062.646 | D20: Market | E20: NY | F20: Fixed Income | G20: Microsoft Corp - 5.2% - Jun 2039 | H20: Bond | J20: Buy | K20: 1044.1575 | L20: 23 | M20: -20522.61 | O20: According to Bond strategy | P20: -1 | Q20: 0.8467 | R20: =M20*Q20 -> -17376.494 | S20: =ABS(R20) -> 17376.494 | T20: =S20/1000000 -> 0.017376494 | Y20: Long MSFT 2039 for rate-cut convexity and carry. Premium justified by high coupon vs market yield; benefit from long-end yield compression. | AI20: Bond strategy
A21: 20 | B21: Wanchun Cui | C21: 46062.646 | D21: Market | E21: NY | F21: Fixed Income | G21: Apple Inc - 1.700% - Aug 2031 | H21: Bond | J21: Buy | K21: 888.02 | L21: 27 | M21: -20303 | O21: According to Bond strategy | P21: -1 | Q21: 0.8467 | R21: =M21*Q21 -> -17190.55 | S21: =ABS(R21) -> 17190.55 | T21: =S21/1000000 -> 0.01719055 | Y21: Buy Apple 2031 as a low-coupon IG bond with high duration. Positioned to benefit from potential rate cuts; strong balance sheet limits credit risk. | AI21: Bond strategy
A22: 21 | B22: Wanchun Cui | C22: 46062.646 | D22: Market | E22: NY | F22: Fixed Income | G22: Ford Motor Co. - 7.500% - Aug 2026 | H22: Bond | J22: Buy | K22: 1012.2 | L22: 20 | M22: -17161.41 | O22: According to Bond strategy | P22: -1 | Q22: 0.8467 | R22: =M22*Q22 -> -14530.566 | S22: =ABS(R22) -> 14530.566 | T22: =S22/1000000 -> 0.014530566 | Y22: Long Ford 7.5% Aug-2026 for short-dated high-carry credit exposure. Trade focuses on yield capture and pull-to-par with limited duration risk, supported by near-term maturity and manageable refinancing profile. | AI22: Bond strategy
A23: 22 | B23: Wanchun Cui | C23: 46062.646 | D23: Market | E23: NY | F23: Fixed Income | G23: Kraft Heinz Foods - 6.500% - Feb 2040 | H23: Bond | J23: Buy | K23: 1084.61 | L23: 19 | M23: -17445.52 | O23: According to Bond strategy | P23: -1 | Q23: 0.8467 | R23: =M23*Q23 -> -14771.122 | S23: =ABS(R23) -> 14771.122 | T23: =S23/1000000 -> 0.014771122 | Y23: Long Kraft Heinz 6.5% Feb-2040 to capture high coupon carry and defensive consumer-staples credit exposure. Position targets income-driven returns with moderate duration sensitivity, supported by resilient cash flows and non-cyclical demand. | AI23: Bond strategy
A24: 23 | B24: Wanchun Cui | C24: 46062.646 | D24: Market | E24: NY | F24: Fixed Income | G24: Altria Group Inc - 9.95% - Nov 2038 | H24: Bond | J24: Buy | K24: 1366.1 | L24: 12 | M24: -14126.58 | O24: According to Bond strategy | P24: -1 | Q24: 0.8467 | R24: =M24*Q24 -> -11960.975 | S24: =ABS(R24) -> 11960.975 | T24: =S24/1000000 -> 0.011960975 | Y24: High-carry defensive credit. Locking ~10% coupon from stable cash-flow issuer to anchor portfolio yield and offset rate/tech volatility. | AI24: Bond strategy
A25: 24 | B25: Wanchun Cui | C25: 46062.646 | D25: Market | E25: NY | F25: Fixed Income | G25: Philip Morris - 6.375% - May 2038 | H25: Bond | J25: Buy | K25: 1114.28 | L25: 15 | M25: -14335.98 | O25: According to Bond strategy | P25: -1 | Q25: 0.8467 | R25: =M25*Q25 -> -12138.274 | S25: =ABS(R25) -> 12138.274 | T25: =S25/1000000 -> 0.012138274 | Y25: High-carry defensive credit. Stable global tobacco cash flows support attractive income and portfolio yield stabilization. | AI25: Bond strategy
A26: 25 | B26: Wanchun Cui | C26: 46062.646 | D26: Market | E26: NY | F26: Fixed Income | G26: Boeing | H26: Bond | J26: Buy | K26: 1090 | L26: 15 | M26: -14118.6 | O26: According to Bond strategy | P26: -1 | Q26: 0.8467 | R26: =M26*Q26 -> -11954.219 | S26: =ABS(R26) -> 11954.219 | T26: =S26/1000000 -> 0.011954219 | Y26: Cyclical recovery credit with elevated carry. Position targets spread compression as Boeing normalizes operations and cash flow over the cycle. | AI26: Bond strategy
A27: 26 | B27: Wanchun Cui | C27: 46062.646 | D27: Market | E27: NY | F27: Fixed Income | G27: United States Steel Corp - 6.875% - Mar 2029 | H27: Bond | J27: Buy | K27: 1004.57 | L27: 10 | M27: -8759.24 | O27: According to Bond strategy | P27: -1 | Q27: 0.8467 | R27: =M27*Q27 -> -7416.4485 | S27: =ABS(R27) -> 7416.4485 | T27: =S27/1000000 -> 0.0074164485 | Y27: Short-dated cyclical credit capturing high carry with limited duration risk. Trade targets stable income and near-term spread normalization into 2029 maturity. | AI27: Bond strategy
A28: 27 | B28: Wanchun Cui | C28: 46062.646 | D28: Market | E28: NY | F28: Fixed Income | G28: JPMORGAN CHASE & CO - 6.4% - May 2038 | H28: Bond | J28: Buy | K28: 1125.29 | L28: 10 | M28: -9652.51 | O28: According to Bond strategy | P28: -1 | Q28: 0.8467 | R28: =M28*Q28 -> -8172.7802 | S28: =ABS(R28) -> 8172.7802 | T28: =S28/1000000 -> 0.0081727802 | Y28: Long JPM 6.4% May-2038 as a credit relative value anchor. High coupon provides strong carry while long maturity offers duration exposure. Position expresses bank credit stability with limited idiosyncratic risk and benefits from spread compression or long-end yield declines. | AI28: Bond strategy
A29: 28 | B29: Wanchun Cui | C29: 46062.646 | D29: Market | E29: NY | F29: Fixed Income | G29: JPMORGAN CHASE & CO - 5.5% - Oct 2040 | H29: Bond | J29: Buy | K29: 1045.52 | L29: 8 | M29: -7199.29 | O29: According to Bond strategy | P29: -1 | Q29: 0.8467 | R29: =M29*Q29 -> -6095.6388 | S29: =ABS(R29) -> 6095.6388 | T29: =S29/1000000 -> 0.0060956388 | Y29: Long JPM 5.5% Oct-2040 to extend bank credit duration with stable carry. Position targets long-end rate sensitivity and potential credit spread tightening while maintaining exposure to a high-quality global systemically important bank. | AI29: Bond strategy
A30: 29 | B30: Jade Sancho | C30: 46062.908 | D30: Limit | E30: NY | F30: Option | G30: Microsoft | H30: Call | I30: Long | J30: Sell | K30: 18.85 | L30: -50 | M30: 79801.2 | O30: Let's see where volatility brings us | P30: -1 | Q30: 0.8467 | R30: =M30*Q30 -> 67567.676 | S30: =ABS(R30) -> 67567.676 | T30: =S30/1000000 -> 0.067567676 | Y30: The price of Microsoft went up again like predicted, it is time to close the call as we have made the expected profit to not take any further risk. | AI30: Bond strategy
A31: 30 | B31: Wanchun Cui | C31: 46062.917 | D31: Market | E31: NY | F31: Fixed Income | G31: OAT 3.250% 25-May-2045 | H31: Bond | J31: Buy | K31: 888.3 | L31: 16 | M31: -14318.22 | O31: According to Bond strategy | P31: -1 | Q31: 1 | R31: =M31*Q31 -> -14318.22 | S31: =ABS(R31) -> 14318.22 | T31: =S31/1000000 -> 0.01431822 | Y31: Adding ultra-long French OAT for Eurozone duration and convexity. Positioned for ECB easing and growth slowdown. Offers yield pickup versus Bunds while maintaining core sovereign risk profile. Complements German and US long-duration exposure. | AI31: Bond strategy
A32: 31 | B32: Wanchun Cui | C32: 46062.917 | D32: Market | E32: NY | F32: Fixed Income | G32: ASML Holding - 2.250% - May 2032 | H32: Bond | J32: Buy | K32: 968.99 | L32: 18 | M32: -17532.81 | O32: According to Bond strategy | P32: -1 | Q32: 1 | R32: =M32*Q32 -> -17532.81 | S32: =ABS(R32) -> 17532.81 | T32: =S32/1000000 -> 0.01753281 | Y32: Long ASML 2.25% May-2032 to gain high-quality tech IG exposure with moderate duration. Trade focuses on spread stability and rate sensitivity, supported by ASML’s monopoly-like industry position and strong balance sheet. | AI32: Bond strategy
A33: 32 | B33: Wanchun Cui | C33: 46062.917 | D33: Market | E33: NY | F33: Fixed Income | G33: Sanofi S.A - 1.875% - Mar 2038 | H33: Bond | J33: Buy | K33: 842.85 | L33: 8 | M33: -6799.92 | O33: According to Bond strategy | P33: -1 | Q33: 1 | R33: =M33*Q33 -> -6799.92 | S33: =ABS(R33) -> 6799.92 | T33: =S33/1000000 -> 0.00679992 | Y33: Non-financial IG anchor in Credit RV bucket. Defensive pharma cash flows with low beta. Used as spread benchmark versus bank credit to isolate financial sector-specific spread moves. | AI33: Bond strategy
A34: 33 | B34: Wanchun Cui | C34: 46062.917 | D34: Market | E34: NY | F34: Fixed Income | G34: TotalEnergies Capital Intl. - 1.535% - May 2039 | H34: Bond | J34: Buy | K34: 753 | L34: 6 | M34: -4535.41 | O34: According to Bond strategy | P34: -1 | Q34: 1 | R34: =M34*Q34 -> -4535.41 | S34: =ABS(R34) -> 4535.41 | T34: =S34/1000000 -> 0.00453541 | Y34: Non-financial IG energy credit added as macro-sensitive leg in Credit RV bucket. Provides diversification from tech and financials while linking portfolio to inflation and commodity dynamics. | AI34: Bond strategy
C35: 46063.012 | D35: CouponPayment | E35: Asia | F35: Fixed Income | G35: Kraft Heinz Foods - 6.500% - Feb 2040 | H35: Bond | J35: Buy | K35: 522.83542 | L35: 1 | M35: 522.84 | O35: According to Bond strategy | P35: -1 | Q35: 0.84269 | R35: =M35*Q35 -> 440.59204 | S35: =ABS(R35) -> 440.59204
A36: 34 | B36: Wanchun Cui | C36: 46063.125 | D36: Market | E36: Asia | F36: Fixed Income | G36: BUND 4.750% 04-Jul-2040 | H36: Bond | J36: Buy | K36: 1183.59 | L36: 12 | M36: -14256.18 | O36: According to Bond strategy | P36: -1 | Q36: 1 | R36: =M36*Q36 -> -14256.18 | S36: =ABS(R36) -> 14256.18 | T36: =S36/1000000 -> 0.01425618 | Y36: Non-financial IG energy credit added as macro-sensitive leg in Credit RV bucket. Provides diversification from tech and financials while linking portfolio to inflation and commodity dynamics.
A37: 35 | B37: Jade Sancho | C37: 46063.664 | D37: Limit | E37: NY | F37: Option | G37: Meta | H37: Call | I37: Long | J37: Buy | K37: 12.6 | L37: 50 | M37: -52892.73 | O37: Let's see where volatility brings us | P37: -1 | Q37: 0.83957 | R37: =M37*Q37 -> -44407.149 | S37: =ABS(R37) -> 44407.149 | T37: =S37/1000000 -> 0.044407149 | Y37: I used a call option on Meta to express a short-term bullish view following a market correction, benefiting from a potential rebound while keeping downside risk limited to the option premium
A38: 36 | B38: Jade Sancho | C38: 46063.719 | D38: Limit | E38: NY | F38: Option | G38: Microsoft | H38: Call | I38: Long | J38: Buy | K38: 6.05 | L38: 50 | M38: -25396.91 | O38: Let's see where volatility brings us | P38: -1 | Q38: 0.83957 | R38: =M38*Q38 -> -21322.484 | S38: =ABS(R38) -> 21322.484 | T38: =S38/1000000 -> 0.021322484 | Y38: Expect Microsoft to go up again as it is only rising since 5 february after crash
A39: 37 | B39: Wang Jialei | C39: 46063.742 | D39: Market | E39: NY | F39: Equities | G39: Netflix Inc. | H39: Equity | J39: Buy | K39: 83.42 | L39: 400 | M39: -28014.68 | O39: Looking for a 10% profit | P39: -1 | Q39: 0.83957 | R39: =M39*Q39 -> -23520.285 | S39: =ABS(R39) -> 23520.285 | T39: =S39/1000000 -> 0.023520285 | U39: =M39/1000000 -> -0.02801468 | V39: Safe haven | W39: Netflix is showing a downward tendency, wait for its future comback | X39: Its acqurition of Warner Bros | Y39: Its plan of acquiring WB show big potential of profitability | Z39: middle term | AA39: Confident | AI39: Long-only | AJ39: 5m
C40: 46069.015 | D40: CouponPayment | E40: Asia | F40: Fixed Income | G40: BUND 1.250% 15-Nov-2048 | H40: Bond | J40: Buy | K40: 137.5 | L40: 1 | M40: 137.5 | O40: According to Bond strategy | P40: -1 | Q40: 1 | R40: =M40*Q40 -> 137.5 | S40: =ABS(R40) -> 137.5 | T40: =S40/1000000 -> 0.0001375
A41: 38 | B41: Jade Sancho | C41: 46070.711 | D41: Market | E41: NY | F41: Option | G41: Meta | H41: Put | I41: Long | J41: Buy | K41: 8.65 | L41: 50 | M41: -36498.2 | P41: -1 | Q41: 0.84389 | R41: =M41*Q41 -> -30800.466 | S41: =ABS(R41) -> 30800.466 | T41: =S41/1000000 -> 0.030800466 | Y41: To go against the call on meta placed
A42: 39 | B42: Jade Sancho | C42: 46070.715 | D42: Market | E42: NY | F42: Option | G42: Microsoft | H42: Put | I42: Long | J42: Buy | K42: 4.8 | L42: 50 | M42: -20253.34 | P42: -1 | Q42: 0.84389 | R42: =M42*Q42 -> -17091.591 | S42: =ABS(R42) -> 17091.591 | T42: =S42/1000000 -> 0.017091591 | Y42: To go against the call placed on microsoft that went down because of growing AI costs of company
A43: 40 | B43: Jade Sancho | C43: 46072.01 | D43: Market | E43: Asia | F43: Option | G43: Microsoft | H43: Call | I43: Long | J43: Sell | K43: 0 | L43: -50 | M43: 0 | P43: -1 | Q43: 0.84821 | R43: =M43*Q43 -> 0 | S43: =ABS(R43) -> 0 | T43: =S43/1000000 -> 0 | Y43: Option expired
A44: 41 | B44: Jade Sancho | C44: 46072.01 | D44: Market | E44: Asia | F44: Option | G44: Meta | H44: Call | I44: Long | J44: Sell | K44: 0 | L44: -50 | M44: 0 | P44: -1 | Q44: 0.84821 | R44: =M44*Q44 -> 0 | S44: =ABS(R44) -> 0 | T44: =S44/1000000 -> 0 | Y44: Option expired
A45: 42 | B45: Jade Sancho | C45: 46073.806 | D45: Market | E45: NY | F45: Option | G45: Microsoft | H45: Put | I45: Long | J45: Sell | K45: 1.72 | L45: -50 | M45: 7303.86 | P45: -1 | Q45: 0.84929 | R45: =M45*Q45 -> 6203.0953 | S45: =ABS(R45) -> 6203.0953 | T45: =S45/1000000 -> 0.0062030953 | Y45: Close position as as it's falling down
A46: 43 | B46: Jade Sancho | C46: 46073.806 | D46: Market | E46: NY | F46: Option | G46: Meta | H46: Put | I46: Long | J46: Sell | K46: 0.04 | L46: -50 | M46: 169.86 | P46: -1 | Q46: 0.84929 | R46: =M46*Q46 -> 144.2604 | S46: =ABS(R46) -> 144.2604 | T46: =S46/1000000 -> 0.0001442604 | Y46: Close position as as it's falling down
A47: 44 | B47: Wang Jialei | C47: 46080.723 | D47: Market | E47: NY | F47: Equities | G47: Netflix Inc. | H47: Equity | J47: Sell | K47: 93.34 | L47: -400 | M47: 31644.7 | O47: Looking for a 10% profit | P47: -1 | Q47: 0.84757 | R47: =M47*Q47 -> 26821.098 | S47: =ABS(R47) -> 26821.098 | T47: =S47/1000000 -> 0.026821098 | Y47: Sold netflix at +10% of the position
C48: 46083.011 | D48: CouponPayment | E48: Asia | F48: Fixed Income | G48: United States Steel Corp - 6.875% - Mar 2029 | H48: Bond | J48: Buy | K48: 290.84033 | L48: 1 | M48: 290.84 | O48: According to Bond strategy | P48: -1 | Q48: 0.86065 | R48: =M48*Q48 -> 250.31145 | S48: =ABS(R48) -> 250.31145 | T48: =S48/1000000 -> 0.00025031145
C49: 46083.012 | D49: CouponPayment | E49: Asia | F49: Fixed Income | G49: BTP 3.100% 03-Jan-2040 | H49: Bond | J49: Buy | K49: 232.5 | L49: 1 | M49: 232.5 | O49: According to Bond strategy | P49: -1 | Q49: 1 | R49: =M49*Q49 -> 232.5 | S49: =ABS(R49) -> 232.5 | T49: =S49/1000000 -> 0.0002325
A50: 45 | B50: Yannis Khalfi | C50: 46083.669 | D50: Market | E50: NY | F50: Option | G50: SPDR GOLD TRUST ETF | H50: Call | I50: Long | J50: Buy | K50: 11.15 | L50: 10 | M50: -9467.2 | O50: Bull call spread - Looking for top of gold | P50: -1 | Q50: 0.84908 | R50: =M50*Q50 -> -8038.4102 | S50: =ABS(R50) -> 8038.4102 | T50: =S50/1000000 -> 0.0080384102 | W50: Reason is the potential rise of gold as a safe haven. Context of war in IRAN. | Y50: BULL CALL SPREAD ON GOLD LEG 1 | AI50: BULL CALL SPREAD ON GOLD LEG 1
A51: 46 | B51: Yannis Khalfi | C51: 46083.669 | D51: Market | E51: NY | F51: Option | G51: SPDR GOLD TRUST ETF | H51: Call | I51: Short | J51: Buy | K51: 4.15 | L51: -10 | M51: 3523.67 | O51: Bull call spread - Looking for top of gold | P51: -1 | Q51: 0.84908 | R51: =M51*Q51 -> 2991.8777 | S51: =ABS(R51) -> 2991.8777 | T51: =S51/1000000 -> 0.0029918777 | Y51: BULL CALL SPREAD ON GOLD LEG 2 | AI51: BULL CALL SPREAD ON GOLD LEG 2
A52: 47 | B52: Yannis Khalfi | C52: 46083.674 | D52: Market | E52: NY | F52: Option | G52: SPDR GOLD TRUST ETF | H52: Call | I52: Long | J52: Buy | K52: 12.1 | L52: 20 | M52: -20547.65 | O52: Bull call spread - Looking for top of gold | P52: -1 | Q52: 0.84908 | R52: =M52*Q52 -> -17446.599 | S52: =ABS(R52) -> 17446.599 | T52: =S52/1000000 -> 0.017446599 | Y52: BULL CALL SPREAD ON GOLD LEG 1 | AI52: BULL CALL SPREAD ON GOLD LEG 1
A53: 48 | B53: Yannis Khalfi | C53: 46083.674 | D53: Market | E53: NY | F53: Option | G53: SPDR GOLD TRUST ETF | H53: Call | I53: Short | J53: Buy | K53: 4.55 | L53: -20 | M53: 7726.6 | O53: Bull call spread - Looking for top of gold | P53: -1 | Q53: 0.84908 | R53: =M53*Q53 -> 6560.5015 | S53: =ABS(R53) -> 6560.5015 | T53: =S53/1000000 -> 0.0065605015 | Y53: BULL CALL SPREAD ON GOLD LEG 2 | AI53: BULL CALL SPREAD ON GOLD LEG 2
A54: 49 | B54: Yannis Khalfi | C54: 46083.687 | D54: Market | E54: NY | F54: Option | G54: SPDR GOLD TRUST ETF | H54: Call | I54: Long | J54: Buy | K54: 15.15 | L54: 25 | M54: -32158.78 | O54: Bull call spread - Looking for top of gold | P54: -1 | Q54: 0.84908 | R54: =M54*Q54 -> -27305.377 | S54: =ABS(R54) -> 27305.377 | T54: =S54/1000000 -> 0.027305377 | Y54: BULL CALL SPREAD ON GOLD LEG 1 | AI54: BULL CALL SPREAD ON GOLD LEG 1
A55: 50 | B55: Yannis Khalfi | C55: 46083.687 | D55: Market | E55: NY | F55: Option | G55: SPDR GOLD TRUST ETF | H55: Call | I55: Short | J55: Buy | K55: 7.75 | L55: -25 | M55: 16450.86 | O55: Bull call spread - Looking for top of gold | P55: -1 | Q55: 0.84908 | R55: =M55*Q55 -> 13968.096 | S55: =ABS(R55) -> 13968.096 | T55: =S55/1000000 -> 0.013968096 | Y55: BULL CALL SPREAD ON GOLD LEG 2 | AI55: BULL CALL SPREAD ON GOLD LEG 2
A56: 51 | B56: Yannis Khalfi | C56: 46084.76 | D56: Market | E56: NY | F56: Equities | G56: Exelon Corp | H56: Equity | J56: Buy | K56: 48.55 | L56: 650 | M56: -26984.22 | O56: Long short Momentum value | P56: -1 | Q56: 0.85508 | R56: =M56*Q56 -> -23073.667 | S56: =ABS(R56) -> 23073.667 | T56: =S56/1000000 -> 0.023073667 | X56: LONG SHORT STRATEGY | AI56: Long Short Momentum Value
A57: 52 | B57: Yannis Khalfi | C57: 46084.76 | D57: Market | E57: NY | F57: Equities | G57: SIRI | H57: Equity | J57: Buy | K57: 21.63 | L57: 958 | M57: -17718.59 | O57: Long short Momentum value | P57: -1 | Q57: 0.85508 | R57: =M57*Q57 -> -15150.812 | S57: =ABS(R57) -> 15150.812 | T57: =S57/1000000 -> 0.015150812 | AI57: Long Short Momentum Value
A58: 53 | B58: Yannis Khalfi | C58: 46084.761 | D58: Market | E58: NY | F58: Equities | G58: Kraft Heinz Co | H58: Equity | J58: Buy | K58: 24.1 | L58: 815 | M58: -16795.07 | O58: Long short Momentum value | P58: -1 | Q58: 0.85508 | R58: =M58*Q58 -> -14361.128 | S58: =ABS(R58) -> 14361.128 | T58: =S58/1000000 -> 0.014361128 | AI58: Long Short Momentum Value
A59: 54 | B59: Yannis Khalfi | C59: 46084.761 | D59: Market | E59: NY | F59: Equities | G59: Xcel Energy, In... | H59: Equity | J59: Buy | K59: 82.75 | L59: 160 | M59: -11321.27 | O59: Long short Momentum value | P59: -1 | Q59: 0.85508 | R59: =M59*Q59 -> -9680.5916 | S59: =ABS(R59) -> 9680.5916 | T59: =S59/1000000 -> 0.0096805916 | AI59: Long Short Momentum Value
A60: 55 | B60: Yannis Khalfi | C60: 46084.762 | D60: Market | E60: NY | F60: Equities | G60: American Electr... | H60: Equity | J60: Buy | K60: 131.45 | L60: 99 | M60: -11127.64 | O60: Long short Momentum value | P60: -1 | Q60: 0.85508 | R60: =M60*Q60 -> -9515.0224 | S60: =ABS(R60) -> 9515.0224 | T60: =S60/1000000 -> 0.0095150224 | AI60: Long Short Momentum Value
A61: 56 | B61: Yannis Khalfi | C61: 46084.762 | D61: Market | E61: NY | F61: Equities | G61: Trip.com Group ... | H61: Equity | J61: Buy | K61: 51.25 | L61: 188 | M61: -8238.7 | O61: Long short Momentum value | P61: -1 | Q61: 0.85508 | R61: =M61*Q61 -> -7044.7476 | S61: =ABS(R61) -> 7044.7476 | T61: =S61/1000000 -> 0.0070447476 | AI61: Long Short Momentum Value
A62: 57 | B62: Yannis Khalfi | C62: 46084.764 | D62: Market | E62: NY | F62: Equities | G62: Biogen Inc | H62: Equity | J62: Buy | K62: 183.66 | L62: 50 | M62: -7852.21 | O62: Long short Momentum value | P62: -1 | Q62: 0.85508 | R62: =M62*Q62 -> -6714.2677 | S62: =ABS(R62) -> 6714.2677 | T62: =S62/1000000 -> 0.0067142677 | AI62: Long Short Momentum Value
A63: 58 | B63: Yannis Khalfi | C63: 46084.765 | D63: Market | E63: NY | F63: Equities | G63: JD.com Inc - | H63: Equity | J63: Buy | K63: 25.39 | L63: 336 | M63: -7294.73 | O63: Long short Momentum value | P63: -1 | Q63: 0.85508 | R63: =M63*Q63 -> -6237.5777 | S63: =ABS(R63) -> 6237.5777 | T63: =S63/1000000 -> 0.0062375777 | AI63: Long Short Momentum Value
A64: 59 | B64: Yannis Khalfi | C64: 46084.765 | D64: Market | E64: NY | F64: Equities | G64: Cognizant Techn.. | H64: Equity | J64: Buy | K64: 63.68 | L64: 132 | M64: -7187.6 | O64: Long short Momentum value | P64: -1 | Q64: 0.85508 | R64: =M64*Q64 -> -6145.973 | S64: =ABS(R64) -> 6145.973 | T64: =S64/1000000 -> 0.006145973 | AI64: Long Short Momentum Value
A65: 60 | B65: Yannis Khalfi | C65: 46084.765 | D65: Market | E65: NY | F65: Equities | G65: Moderna Inc | H65: Equity | J65: Buy | K65: 49.67 | L65: 168 | M65: -7135.27 | O65: Long short Momentum value | P65: -1 | Q65: 0.85508 | R65: =M65*Q65 -> -6101.2267 | S65: =ABS(R65) -> 6101.2267 | T65: =S65/1000000 -> 0.0061012267 | AI65: Long Short Momentum Value
A66: 61 | B66: Yannis Khalfi | C66: 46084.766 | D66: Market | E66: NY | F66: Equities | G66: Skyworks Soluti... | H66: Equity | J66: Buy | K66: 57.85 | L66: 133 | M66: -6579.04 | O66: Long short Momentum value | P66: -1 | Q66: 0.85508 | R66: =M66*Q66 -> -5625.6055 | S66: =ABS(R66) -> 5625.6055 | T66: =S66/1000000 -> 0.0056256055 | AI66: Long Short Momentum Value
A67: 62 | B67: Yannis Khalfi | C67: 46084.766 | D67: Market | E67: NY | F67: Equities | G67: Baidu Inc - ADR | H67: Equity | J67: Buy | K67: 118.23 | L67: 63 | M67: -6369.06 | O67: Long short Momentum value | P67: -1 | Q67: 0.85508 | R67: =M67*Q67 -> -5446.0558 | S67: =ABS(R67) -> 5446.0558 | T67: =S67/1000000 -> 0.0054460558 | AI67: Long Short Momentum Value
A68: 63 | B68: Yannis Khalfi | C68: 46084.767 | D68: Market | E68: NY | F68: Equities | G68: Comcast Corp - ... | H68: Equity | J68: Buy | K68: 30.84 | L68: 229 | M68: -6038.89 | O68: Long short Momentum value | P68: -1 | Q68: 0.85508 | R68: =M68*Q68 -> -5163.7341 | S68: =ABS(R68) -> 5163.7341 | T68: =S68/1000000 -> 0.0051637341 | AI68: Long Short Momentum Value
... A108: 103 | B108: Yannis Khalfi | C108: 46084.783 | D108: Market | E108: NY | F108: Equities | G108: Dexcom Inc | H108: Equity | J108: Buy | K108: 72.6 | L108: 237 | M108: -14712.69 | O108: Long short Momentum value | P108: -1 | Q108: 0.85508 | R108: =M108*Q108 -> -12580.527 | S108: =ABS(R108) -> 12580.527 | T108: =S108/1000000 -> 0.012580527 | AI108: Long Short Momentum Value
C109: 46085.25 | D109: Dividends | E109: NY | F109: Equities | G109: PayPal Holdings... | H109: Equity | J109: Buy | K109: 0.14 | L109: 36 | M109: 4.34 | O109: Long short Momentum value | P109: 0 | Q109: 0.8615 | R109: =M109*Q109 -> 3.73891 | S109: =ABS(R109) -> 3.73891 | T109: =S109/1000000 -> 3.73891e-06 | AI109: Long Short Momentum Value
C110: 46085.25 | D110: Dividends | E110: NY | F110: Equities | G110: Fox Corporation.. | H110: Equity | J110: Buy | K110: 0.28 | L110: 106 | M110: 25.54 | O110: Long short Momentum value | P110: 0 | Q110: 0.8615 | R110: =M110*Q110 -> 22.00271 | S110: =ABS(R110) -> 22.00271 | T110: =S110/1000000 -> 2.200271e-05 | AI110: Long Short Momentum Value
C111: 46085.25 | D111: Dividends | E111: NY | F111: Equities | G111: Lam Research Co... | H111: Equity | J111: Buy | K111: 0.26 | L111: 55 | M111: 12.31 | O111: Long short Momentum value | P111: 0 | Q111: 0.8615 | R111: =M111*Q111 -> 10.605065 | S111: =ABS(R111) -> 10.605065 | T111: =S111/1000000 -> 1.0605065e-05 | AI111: Long Short Momentum Value
C112: 46085.25 | D112: Dividends | E112: NY | F112: Equities | G112: Qualcomm, Inc. | H112: Equity | J112: Buy | K112: 0.89 | L112: 58 | M112: 44.36 | O112: Long short Momentum value | P112: 0 | Q112: 0.8615 | R112: =M112*Q112 -> 38.21614 | S112: =ABS(R112) -> 38.21614 | T112: =S112/1000000 -> 3.821614e-05 | AI112: Long Short Momentum Value
A113: 104 | B113: Yannis Khalfi | C113: 46086.812 | D113: Market | E113: NY | F113: Option | G113: SPDR GOLD TRUST ETF | H113: Call | I113: Short | J113: Sell | K113: 0.11 | L113: 30 | M113: -283.61 | O113: Bull call spread - Looking for top of gold | P113: -1 | Q113: 0.85942 | R113: =M113*Q113 -> -243.74011 | S113: =ABS(R113) -> 243.74011 | T113: =S113/1000000 -> 0.00024374011 | AI113: Long Short Momentum Value
C114: 46087.25 | D114: Dividends | E114: NY | F114: Equities | G114: Kraft Heinz Co | H114: Equity | J114: Buy | K114: 0.4 | L114: 815 | M114: 280.85 | O114: Long short Momentum value | P114: 0 | Q114: 0.8615 | R114: =M114*Q114 -> 241.95228 | S114: =ABS(R114) -> 241.95228 | T114: =S114/1000000 -> 0.00024195228 | AI114: Long Short Momentum Value
C115: 46087.25 | D115: Dividends | E115: NY | F115: Equities | G115: EBay Inc. | H115: Equity | J115: Buy | K115: 0.31 | L115: 134 | M115: 35.79 | O115: Long short Momentum value | P115: 0 | Q115: 0.8615 | R115: =M115*Q115 -> 30.833085 | S115: =ABS(R115) -> 30.833085 | T115: =S115/1000000 -> 3.0833085e-05 | X115: CUT THAT AT +18% | Y115: Max month history was +20% | AI115: Long Short Momentum Value
A116: 105 | B116: Yannis Khalfi | C116: 46087.768 | D116: Market | E116: NY | F116: Equities | G116: Marvell Technol. | H116: Equity | J116: Sell | K116: 91.76 | L116: -30 | M116: 2371.53 | O116: Long short Momentum value | P116: -1 | Q116: 0.8615 | R116: =M116*Q116 -> 2043.0731 | S116: =ABS(R116) -> 2043.0731 | T116: =S116/1000000 -> 0.0020430731 | X116: CUT THAT ONE AT +12% | Y116: Max month in history was + 33% and was at IPO | AI116: Long Short Momentum Value
A117: 106 | B117: Yannis Khalfi | C117: 46087.768 | D117: Market | E117: NY | F117: Equities | G117: Okta Inc - Ordi... | H117: Equity | J117: Sell | K117: 80.63 | L117: -64 | M117: 4445.6 | O117: Long short Momentum value | P117: -1 | Q117: 0.8615 | R117: =M117*Q117 -> 3829.8844 | S117: =ABS(R117) -> 3829.8844 | T117: =S117/1000000 -> 0.0038298844
A118: 107 | B118: Yannis Khalfi | C118: 46088.011 | D118: Market | E118: NY | F118: Option | G118: SPDR GOLD TRUST ETF | H118: Call | I118: Long | J118: Sell | K118: 0 | L118: -30 | M118: 0 | O118: Bull call spread - Looking for top of gold | Q118: 0.86122 | R118: =M118*Q118 -> 0 | S118: =ABS(R118) -> 0 | T118: =S118/1000000 -> 0
C119: 46090.208 | D119: Dividends | E119: Asia | F119: Equities | G119: Alphabet Inc - | H119: Equity | J119: Buy | K119: 0.21 | L119: 17 | M119: 3.1 | O119: Long short Momentum value | P119: -1 | Q119: 0.86521 | R119: =M119*Q119 -> 2.682151 | S119: =ABS(R119) -> 2.682151 | T119: =S119/1000000 -> 2.682151e-06
A120: 108 | B120: Wanchun Cui | C120: 46091.76 | D120: Market | E120: NY | F120: Cryptos | G120: SOL | H120: Crypto | J120: Buy | K120: 88.35 | L120: 112.8286 | M120: -8559.73 | P120: -1 | Q120: 0.85869 | R120: =M120*Q120 -> -7350.1546 | S120: =ABS(R120) -> 7350.1546 | T120: =S120/1000000 -> 0.0073501546
A121: 109 | B121: Wanchun Cui | C121: 46091.76 | D121: Market | E121: NY | F121: Cryptos | G121: RNDR | H121: Crypto | J121: Buy | K121: 1.566 | L121: 6385.696 | M121: -8586.86 | P121: -1 | Q121: 0.85869 | R121: =M121*Q121 -> -7373.4508 | S121: =ABS(R121) -> 7373.4508 | T121: =S121/1000000 -> 0.0073734508
A122: 110 | B122: Wanchun Cui | C122: 46091.76 | D122: Market | E122: NY | F122: Cryptos | G122: FET | H122: Crypto | J122: Buy | K122: 0.1549 | L122: 38885.288 | M122: -5172.15 | P122: -1 | Q122: 0.85869 | R122: =M122*Q122 -> -4441.2735 | S122: =ABS(R122) -> 4441.2735 | T122: =S122/1000000 -> 0.0044412735
A123: 111 | B123: Wanchun Cui | C123: 46091.76 | D123: Market | E123: NY | F123: Cryptos | G123: UNI | H123: Crypto | J123: Buy | K123: 3.925 | L123: 1273.8854 | M123: -4293.43 | P123: -1 | Q123: 0.85869 | R123: =M123*Q123 -> -3686.7254 | S123: =ABS(R123) -> 3686.7254 | T123: =S123/1000000 -> 0.0036867254
A124: 112 | B124: Wanchun Cui | C124: 46091.76 | D124: Market | E124: NY | F124: Cryptos | G124: LINK | H124: Crypto | J124: Buy | K124: 9.16 | L124: 436.443 | M124: -3433.25 | P124: -1 | Q124: 0.85869 | R124: =M124*Q124 -> -2948.0974 | S124: =ABS(R124) -> 2948.0974 | T124: =S124/1000000 -> 0.0029480974
A125: 113 | B125: Wanchun Cui | C125: 46091.76 | D125: Market | E125: NY | F125: Cryptos | G125: OP | H125: Crypto | J125: Buy | K125: 0.123 | L125: 40650.406 | M125: -4293.43 | P125: -1 | Q125: 0.85869 | R125: =M125*Q125 -> -3686.7254 | S125: =ABS(R125) -> 3686.7254 | T125: =S125/1000000 -> 0.0036867254
A126: 114 | B126: Yannis Khalfi | C126: 46092.747 | D126: Market | E126: NY | F126: Option | G126: SPDR GOLD TRUST ETF | H126: Call | I126: Short | J126: Sell | K126: 0.15 | L126: 25 | M126: -322.98 | O126: Bull call spread - Looking for top of gold | P126: -1 | Q126: 0.86129 | R126: =M126*Q126 -> -278.17944 | S126: =ABS(R126) -> 278.17944 | T126: =S126/1000000 -> 0.00027817944
C127: 46094.208 | D127: Dividends | E127: Asia | F127: Equities | G127: Xcel Energy, In... | H127: Equity | J127: Buy | K127: 0.5925 | L127: 160 | M127: 82.33 | P127: -1 | Q127: 0.86521 | R127: =M127*Q127 -> 71.232739 | S127: =ABS(R127) -> 71.232739 | T127: =S127/1000000 -> 7.1232739e-05
A128: 115 | B128: Yannis Khalfi | C128: 46094.769 | D128: Market | E128: NY | F128: Equities | G128: JD.com Inc - | H128: Equity | J128: Sell | K128: 28.28 | L128: -336 | M128: 8251.91 | P128: -1 | Q128: 0.86843 | R128: =M128*Q128 -> 7166.2062 | S128: =ABS(R128) -> 7166.2062 | T128: =S128/1000000 -> 0.0071662062
A129: 116 | B129: Yannis Khalfi | C129: 46094.769 | D129: Market | E129: NY | F129: Equities | G129: Micron Technolo... | H129: Equity | J129: Sell | K129: 422.52 | L129: -5 | M129: 1834.65 | P129: -1 | Q129: 0.86843 | R129: =M129*Q129 -> 1593.2651 | S129: =ABS(R129) -> 1593.2651 | T129: =S129/1000000 -> 0.0015932651
C130: 46097.208 | D130: Dividends | E130: Asia | F130: Equities | G130: NetEase Inc - | H130: Equity | J130: Buy | K130: 1.16 | L130: 1 | M130: 1.01 | Q130: 0.86521 | R130: =M130*Q130 -> 0.8738621 | S130: =ABS(R130) -> 0.8738621 | T130: =S130/1000000 -> 8.738621e-07
A131: 117 | B131: Yannis Khalfi | C131: 46094.969 | D131: Market | E131: Asia | F131: Option | G131: SPDR GOLD TRUST ETF | H131: Call | I131: Long | J131: Sell | K131: 0 | L131: -25 | M131: 0 | P131: 0 | Q131: 0.87608 | R131: =M131*Q131 -> 0 | S131: =ABS(R131) -> 0 | T131: =S131/1000000 -> 0
A132: 118 | B132: Yannis Khalfi | C132: 46097.685 | D132: Market | E132: NY | F132: Equities | G132: Intel Corp. | H132: Equity | J132: Sell | K132: 48.43 | L132: -96 | M132: 4068.04 | P132: -1 | Q132: 0.87498 | R132: =M132*Q132 -> 3559.4536 | S132: =ABS(R132) -> 3559.4536 | T132: =S132/1000000 -> 0.0035594536
A133: 119 | B133: Wanchun Cui | C133: 46098.724 | D133: Market | E133: NY | F133: Cryptos | G133: FET | H133: Crypto | J133: Buy | K133: 0.2308 | L133: 59895.833 | M133: -12015.09 | P133: -1 | Q133: 0.86915 | R133: =M133*Q133 -> -10442.915 | S133: =ABS(R133) -> 10442.915 | T133: =S133/1000000 -> 0.010442915
A134: 120 | B134: Wanchun Cui | C134: 46098.724 | D134: Market | E134: NY | F134: Cryptos | G134: SOL | H134: Crypto | J134: Buy | K134: 94.7 | L134: 121.4489 | M134: -9996.27 | P134: -1 | Q134: 0.86915 | R134: =M134*Q134 -> -8688.2581 | S134: =ABS(R134) -> 8688.2581 | T134: =S134/1000000 -> 0.0086882581
A135: 121 | B135: Wanchun Cui | C135: 46098.724 | D135: Market | E135: NY | F135: Cryptos | G135: RNDR | H135: Crypto | J135: Buy | K135: 1.8 | L135: 6388.8889 | M135: -9995.22 | P135: -1 | Q135: 0.86915 | R135: =M135*Q135 -> -8687.3455 | S135: =ABS(R135) -> 8687.3455 | T135: =S135/1000000 -> 0.0086873455
A136: 122 | B136: Wanchun Cui | C136: 46098.724 | D136: Market | E136: NY | F136: Cryptos | G136: LINK | H136: Crypto | J136: Buy | K136: 9.86 | L136: 1049.2701 | M136: -8992.05 | P136: -1 | Q136: 0.86915 | R136: =M136*Q136 -> -7815.4403 | S136: =ABS(R136) -> 7815.4403 | T136: =S136/1000000 -> 0.0078154403
A137: 123 | B137: Wanchun Cui | C137: 46098.724 | D137: Market | E137: NY | F137: Cryptos | G137: UNI | H137: Crypto | J137: Buy | K137: 4.008 | L137: 2295.4092 | M137: -7996.18 | P137: -1 | Q137: 0.86915 | R137: =M137*Q137 -> -6949.8798 | S137: =ABS(R137) -> 6949.8798 | T137: =S137/1000000 -> 0.0069498798
A138: 124 | B138: Wanchun Cui | C138: 46098.724 | D138: Market | E138: NY | F138: Cryptos | G138: OP | H138: Crypto | J138: Buy | K138: 0.136 | L138: 68047.337 | M138: -8043.49 | P138: -1 | Q138: 0.86915 | R138: =M138*Q138 -> -6990.9993 | S138: =ABS(R138) -> 6990.9993 | T138: =S138/1000000 -> 0.0069909993
A139: 125 | B139: Wanchun Cui | C139: 46098.724 | D139: Market | E139: NY | F139: Cryptos | G139: BTC | H139: Crypto | J139: Buy | K139: 74320.63 | L139: 0.1238 | M139: -7996.95 | P139: -1 | Q139: 0.86915 | R139: =M139*Q139 -> -6950.5491 | S139: =ABS(R139) -> 6950.5491 | T139: =S139/1000000 -> 0.0069505491
...

Sheet Dashboard
A1: Full trade cycle | B1: Date | C1: Instrument | D1: Asset class | E1: Trader | F1: Net P&L | G1: Net P&L $ | H1: Portfolio wallet currently | I1: Portfolio $ | J1: 1000000 | K1: 1151240
A2: 1 | B2: 46044 | C2: EUR/USD | D2: FX | E2: Yannis Khalfi | F2: -1 | G2: 0
A3: 2 | B3: 46056 | C3: NVDA | D3: Call | E3: Jade Sancho | F3: -23876.22 | G3: -23876.22 | H3: =J1+F3 -> 976123.78 | I3: =J1+G3 -> 976123.78 | J3: Include Longest trade, shortest trade in python
A4: 3 | B4: 46056 | C4: NVDA | D4: Put | E4: Jade Sancho | F4: 25922.51 | G4: 25922.51 | H4: =H3+F4 -> 1002046.3 | I4: =I3+G4 -> 1002046.3 | J4: Include trades on NY / ASIA / LONDON on python
A5: 4 | B5: 46058 | C5: BTC | D5: Crypto | E5: Yannis Khalfi | F5: -3027.66 | G5: -3027.66 | H5: =H4+F5 -> 999018.63 | I5: =I4+G5 -> 999018.63 | J5: Include fees in python yannis
A6: 5 | B6: 46062 | C6: Microsoft | D6: Call | E6: Jade Sancho | F6: 46895.85 | G6: 46895.85 | H6: =H5+F6 -> 1045914.5 | I6: =I5+G6 -> 1045914.5 | J6: CETTE COLONNE PEUT FAIRE CRASH SI JE LA SUPPRIME DONC RECTIFIER CODE SUR EXPECTIF AXIS HAS 10 ELEMENTS, NEW VALUES HAVE 11 ELEMENTS
A7: 8 | B7: =Trading_Journal!C43 -> 46072.01 | C7: Microsoft | D7: Call | E7: Jade Sancho | F7: -25396.9 | G7: -25396.9 | H7: =H6+F7 -> 1020517.6 | I7: =I6+G7 -> 1020517.6
A8: 9 | B8: =Trading_Journal!C44 -> 46072.01 | C8: Meta | D8: Call | E8: Jade Sancho | F8: -52892.72 | G8: -52892.72 | H8: =H7+F8 -> 967624.86 | I8: =I7+G8 -> 967624.86
A9: 10 | B9: =Trading_Journal!C45 -> 46073.806 | C9: Microsoft | D9: Put | E9: Jade Sancho | F9: -12949.48 | G9: -12949.48 | H9: =H8+F9 -> 954675.38 | I9: =I8+G9 -> 954675.38
A10: 11 | B10: =Trading_Journal!C46 -> 46073.806 | C10: Meta | D10: Put | E10: Jade Sancho | F10: -36328.34 | G10: -36328.34 | H10: =H9+F10 -> 918347.04 | I10: =I9+G10 -> 918347.04
A11: 12 | B11: 46080 | C11: Netflix | D11: Equity | E11: Wang Jialei | F11: 3630.02 | G11: 3630.02 | H11: =H10+F11 -> 921977.06 | I11: =I10+G11 -> 921977.06
A12: 19 | B12: 46086 | C12: SPDR GOLD TRUST ETF | D12: Call | E12: Yannis Khalfi | F12: =3429.13+7537.53 -> 10966.66 | G12: =3429.13+7537.53 -> 10966.66 | H12: =H11+F12 -> 932943.72 | I12: =I11+G12 -> 932943.72
A13: 20 | B13: 46087 | C13: Marvell Technol. | D13: Equity | E13: Yannis Khalfi | F13: 360.38 | G13: 360.38 | H13: =H12+F13 -> 933304.1 | I13: =I12+G13 -> 933304.1
A14: 21 | B14: 46087 | C14: Okta Inc - Ordi... | D14: Equity | E14: Yannis Khalfi | F14: 495.54 | G14: 495.54 | H14: =H13+F14 -> 933799.64 | I14: =I13+G14 -> 933799.64
A15: 22 | B15: 46088.011 | C15: SPDR GOLD TRUST ETF | D15: Call | E15: Yannis Khalfi | F15: =-9467.21 - 20547.66 -> -30014.87 | G15: =-9467.21 - 20547.66 -> -30014.87 | H15: =H14+F15 -> 903784.77 | I15: =I14+G15 -> 903784.77
A16: 23 | B16: 46092.747 | C16: SPDR GOLD TRUST ETF | D16: Call | E16: Yannis Khalfi | F16: 16127.88 | G16: 16127.88 | H16: =H15+F16 -> 919912.65 | I16: =I15+G16 -> 919912.65
A17: 24 | B17: 46094.769 | C17: JD.com Inc - | D17: Equity | E17: Yannis Khalfi | F17: 957.18 | G17: 957.18 | H17: =H16+F17 -> 920869.83 | I17: =I16+G17 -> 920869.83
A18: 25 | B18: 46094.769 | C18: Micron Technolo... | D18: Equity | E18: Yannis Khalfi | F18: 199.18 | G18: 199.18 | H18: =H17+F18 -> 921069.01 | I18: =I17+G18 -> 921069.01
A19: 26 | B19: 46094.969 | C19: SPDR GOLD TRUST ETF | D19: Call | E19: Yannis Khalfi | F19: -32158.79 | G19: -32158.79 | H19: =H18+F19 -> 888910.22 | I19: =I18+G19 -> 888910.22
A20: 27 | B20: 46097.685 | C20: Intel Corp. | D20: Equity | E20: Yannis Khalfi | F20: 524.31 | G20: 524.31 | H20: =H19+F20 -> 889434.53 | I20: =I19+G20 -> 889434.53
A21: 28 | B21: 46098.724 | C21: FET | D21: Crypto | E21: Wanchun Cui | F21: 2922.27 | G21: 2922.27 | H21: =H20+F21 -> 892356.8 | I21: =I20+G21 -> 892356.8
A22: 29 | B22: 46099.001 | C22: RNDR | D22: Crypto | E22: Wanchun Cui | F22: =1370.82 - 32.57 -> 1338.25 | G22: =1370.82 - 32.57 -> 1338.25 | H22: =H21+F22 -> 893695.05 | I22: =I21+G22 -> 893695.05
A23: 30 | B23: 46099.001 | C23: GBP/USD | D23: FX | E23: Wang Jialei | F23: =-260.17 -> -260.17 | G23: =-260.17 -> -260.17 | H23: =H22+F23 -> 893434.88 | I23: =I22+G23 -> 893434.88
A24: 31 | B24: 46099.001 | C24: EUR/USD | D24: FX | E24: Wang Jialei | F24: -564.91 | G24: -564.91 | H24: =H23+F24 -> 892869.97 | I24: =I23+G24 -> 892869.97
A25: 32 | B25: 46099.604 | C25: GOLD | D25: Commodity | E25: Yannis Khalfi | F25: -3029.63 | G25: -3029.63 | H25: =H24+F25 -> 889840.34 | I25: =I24+G25 -> 889840.34
A26: 33 | B26: 46099.604 | C26: SILVER | D26: Commodity | E26: Yannis Khalfi | F26: -10538.04 | G26: -10538.04 | H26: =H25+F26 -> 879302.3 | I26: =I25+G26 -> 879302.3
A27: 34 | B27: 46099.657 | C27: BTC | D27: Crypto | E27: Wanchun Cui | F27: -323.25 | G27: -323.25 | H27: =H26+F27 -> 878979.05 | I27: =I26+G27 -> 878979.05
A28: 35 | B28: 46099.657 | C28: LINK | D28: Crypto | E28: Wanchun Cui | F28: =67.57 - 575.61 -> -508.04 | G28: =67.57 - 575.61 -> -508.04 | H28: =H27+F28 -> 878471.01 | I28: =I27+G28 -> 878471.01
A29: 36 | B29: 46099.657 | C29: UNI | D29: Crypto | E29: Wanchun Cui | F29: =-211.25-640.52 -> -851.77 | G29: =-211.25-640.52 -> -851.77 | H29: =H28+F29 -> 877619.24 | I29: =I28+G29 -> 877619.24
A30: 37 | B30: 46099.657 | C30: SOL | D30: Crypto | E30: Wanchun Cui | F30: =179.69 - 589.15+1508.22 -> 1098.76 | G30: =179.69 - 589.15+1508.22 -> 1098.76 | H30: =H29+F30 -> 878718 | I30: =I29+G30 -> 878718
A31: 38 | B31: 46099.657 | C31: OP | D31: Crypto | E31: Wanchun Cui | F31: =-373.3 -> -373.3 | G31: 0 | H31: =H30+F31 -> 878344.7 | I31: =I30+G31 -> 878718
A32: 39 | B32: 46099.657 | C32: BTP 3.100% 03-Jan-2040 | D32: Bond | E32: Wanchun Cui | F32: -309.85 | G32: -309.85 | H32: =H31+F32 -> 878034.85 | I32: =I31+G32 -> 878408.15
A33: 40 | B33: 46099.657 | C33: JPMORGAN CHASE & CO - 5.5% - Oct 2040 | D33: Bond | E33: Wanchun Cui | F33: 56.55 | G33: 56.55 | H33: =H32+F33 -> 878091.4 | I33: =I32+G33 -> 878464.7
A34: 41 | B34: 46099.657 | C34: JPMORGAN CHASE & CO - 6.4% - May 2038 | D34: Bond | E34: Wanchun Cui | F34: 19.74 | G34: 19.74 | H34: =H33+F34 -> 878111.14 | I34: =I33+G34 -> 878484.44
A35: 42 | B35: 46099.657 | C35: Philip Morris - 6.375% - May 2038 | D35: Bond | E35: Wanchun Cui | F35: 121.46 | G35: 121.46 | H35: =H34+F35 -> 878232.6 | I35: =I34+G35 -> 878605.9
A36: 43 | B36: 46099.657 | C36: Boeing | D36: Bond | E36: Wanchun Cui | F36: 590.31 | G36: 590.31 | H36: =H35+F36 -> 878822.91 | I36: =I35+G36 -> 879196.21
A37: 44 | B37: 46099.657 | C37: Ford Motor Co. - 7.500% - Aug 2026 | D37: Bond | E37: Wanchun Cui | F37: 313 | G37: 313 | H37: =H36+F37 -> 879135.91 | I37: =I36+G37 -> 879509.21
A38: 45 | B38: 46099.657 | C38: Apple Inc - 1.700% - Aug 2031 | D38: Bond | E38: Wanchun Cui | F38: 270.69 | G38: 270.69 | H38: =H37+F38 -> 879406.6 | I38: =I37+G38 -> 879779.9
A39: 46 | B39: 46099.657 | C39: United States Steel Corp - 6.875% - Mar 2029 | D39: Bond | E39: Wanchun Cui | F39: 162.71 | G39: 162.71 | H39: =H38+F39 -> 879569.31 | I39: =I38+G39 -> 879942.61
A40: 47 | B40: 46099.657 | C40: Kraft Heinz Foods - 6.500% - Feb 2040 | D40: Bond | E40: Wanchun Cui | F40: 225.91 | G40: 225.91 | H40: =H39+F40 -> 879795.22 | I40: =I39+G40 -> 880168.52
A41: 48 | B41: 46099.657 | C41: Microsoft Corp - 5.2% - Jun 2039 | D41: Bond | E41: Wanchun Cui | F41: 492.78 | G41: 492.78 | H41: =H40+F41 -> 880288 | I41: =I40+G41 -> 880661.3
A42: 49 | B42: 46099.657 | C42: Altria Group Inc - 9.95% - Nov 2038 | D42: Bond | E42: Wanchun Cui | F42: 456.38 | G42: 456.38 | H42: =H41+F42 -> 880744.38 | I42: =I41+G42 -> 881117.68
A43: 50 | B43: 46099.657 | C43: T-BOND 3.125% 15/05/2048 | D43: Bond | E43: Wanchun Cui | F43: =15.47 + 696.17 -> 711.64 | G43: =15.47 + 696.17 -> 711.64 | H43: =H42+F43 -> 881456.02 | I43: =I42+G43 -> 881829.32
A44: 51 | B44: 46099.657 | C44: SOL | D44: Crypto | E44: Wanchun Cui | F44: =-1 -> -1 | G44: 0 | H44: =H43+F44 -> 881455.02 | I44: =I43+G44 -> 881829.32
A45: 52 | B45: 46099.657 | C45: Dexcom Inc | D45: Equity | E45: Yannis Khalfi | F45: -864.04 | G45: -864.04 | H45: =H44+F45 -> 880590.98 | I45: =I44+G45 -> 880965.28
A46: 53 | B46: 46099.657 | C46: Analog Devices ... | D46: Equity | E46: Yannis Khalfi | F46: -89.22 | G46: -89.22 | H46: =H45+F46 -> 880501.76 | I46: =I45+G46 -> 880876.06
A47: 54 | B47: 46099.657 | C47: Microchip Techn... | D47: Equity | E47: Yannis Khalfi | F47: -253.88 | G47: -253.88 | H47: =H46+F47 -> 880247.88 | I47: =I46+G47 -> 880622.18
A48: 55 | B48: 46099.657 | C48: CSX Corp. | D48: Equity | E48: Yannis Khalfi | F48: -346.29 | G48: -346.29 | H48: =H47+F48 -> 879901.59 | I48: =I47+G48 -> 880275.89
A49: 56 | B49: 46099.657 | C49: Xcel Energy, In... | D49: Equity | E49: Yannis Khalfi | F49: -172.8 | G49: -172.8 | H49: =H48+F49 -> 879728.79 | I49: =I48+G49 -> 880103.09
A50: 57 | B50: 46099.657 | C50: Copart, Inc. | D50: Equity | E50: Yannis Khalfi | F50: -324.45 | G50: -324.45 | H50: =H49+F50 -> 879404.34 | I50: =I49+G50 -> 879778.64
A51: 58 | B51: 46099.657 | C51: Regeneron Pharm... | D51: Equity | E51: Yannis Khalfi | F51: -118.88 | G51: -118.88 | H51: =H50+F51 -> 879285.46 | I51: =I50+G51 -> 879659.76
A52: 59 | B52: 46099.657 | C52: Comcast Corp - ... | D52: Equity | E52: Yannis Khalfi | F52: -307.49 | G52: -307.49 | H52: =H51+F52 -> 878977.97 | I52: =I51+G52 -> 879352.27
A53: 60 | B53: 46099.657 | C53: Vertex Pharmace. | D53: Equity | E53: Yannis Khalfi | F53: -267.66 | G53: -267.66 | H53: =H52+F53 -> 878710.31 | I53: =I52+G53 -> 879084.61
A54: 61 | B54: 46099.657 | C54: Dollar Tree Inc | D54: Equity | E54: Yannis Khalfi | F54: -216.21 | G54: -216.21 | H54: =H53+F54 -> 878494.1 | I54: =I53+G54 -> 878868.4
A55: 62 | B55: 46099.657 | C55: Paccar Inc. | D55: Equity | E55: Yannis Khalfi | F55: -292.88 | G55: -292.88 | H55: =H54+F55 -> 878201.22 | I55: =I54+G55 -> 878575.52
A56: 63 | B56: 46099.657 | C56: Cognizant Techn.. | D56: Equity | E56: Yannis Khalfi | F56: -138.83 | G56: -138.83 | H56: =H55+F56 -> 878062.39 | I56: =I55+G56 -> 878436.69
... A101: 108 | B101: 46099.657 | C101: ASML Holding - 2.250% - May 2032 | D101: Bond | E101: Wanchun Cui | F101: -348.3 | G101: -348.3 | H101: =H100+F101 -> 887858.02 | I101: =I100+G101 -> 888233.32
A102: 109 | B102: 46099.657 | C102: BUND 1.250% 15-Nov-2048 | D102: Bond | E102: Wanchun Cui | F102: =-40.56 - 33.3 -> -73.86 | G102: =-40.56 - 33.3 -> -73.86 | H102: =H101+F102 -> 887784.16 | I102: =I101+G102 -> 888159.46
A103: 110 | B103: 46099.657 | C103: TotalEnergies Capital Intl. - 1.535% - May 2039 | D103: Bond | E103: Wanchun Cui | F103: -107.4 | G103: -107.4 | H103: =H102+F103 -> 887676.76 | I103: =I102+G103 -> 888052.06
A104: 111 | B104: 46100.3 | C104: USD/JPY | D104: FX | E104: Wanchun Cui | F104: 758.48 | G104: 758.48 | H104: =H103+F104 -> 888435.24 | I104: =I103+G104 -> 888810.54
A105: 112 | B105: 46100.3 | C105: USD/JPY | D105: FX | E105: Wanchun Cui | F105: -41.85 | G105: -41.85 | H105: =H104+F105 -> 888393.39 | I105: =I104+G105 -> 888768.69
A106: 113 | B106: 46100.625 | C106: SPY | D106: Call | E106: Wanchun Cui | F106: =1361.85+1870.13+899.18 -> 4131.16 | G106: =1361.85+1870.13+899.18 -> 4131.16 | H106: =H105+F106 -> 892524.55 | I106: =I105+G106 -> 892899.85
A107: 114 | B107: 46100.625 | C107: SPY | D107: Call | E107: Wanchun Cui | F107: -1 | G107: 0 | H107: =H106+F107 -> 892523.55 | I107: =I106+G107 -> 892899.85
A108: 115 | B108: 46104.665 | C108: BUND 4.750% 04-Jul-2040 | D108: Bond | E108: Wanchun Cui | F108: =-100.9 - 34.08 -> -134.98 | G108: =-100.9 - 34.08 -> -134.98 | H108: =H107+F108 -> 892388.57 | I108: =I107+G108 -> 892764.87
A109: 116 | B109: 46107.665 | C109: BRENT CRU OIL LASDA MAY 16 | D109: Commodity | E109: Wanchun Cui | F109: 30087.7 | G109: 30087.7 | H109: =H108+F109 -> 922476.27 | I109: =I108+G109 -> 922852.57
A110: 117 | B110: 46107.665 | C110: SOL | D110: Crypto | E110: Wanchun Cui | F110: -1 | G110: 0 | H110: =H109+F110 -> 922475.27 | I110: =I109+G110 -> 922852.57
A111: 118 | B111: 46107.665 | C111: SOL | D111: Crypto | E111: Wanchun Cui | F111: -1 | G111: 0 | H111: =H110+F111 -> 922474.27 | I111: =I110+G111 -> 922852.57
A112: 119 | B112: 46107.667 | C112: CRUDE OIL MAY 16 | D112: Commodity | E112: Wanchun Cui | F112: =-10058.38+21864.4 -> 11806.02 | G112: =-10058.38+21864.4 -> 11806.02 | H112: =H111+F112 -> 934280.29 | I112: =I111+G112 -> 934658.59
A113: 120 | B113: 46107.657 | C113: FET | D113: Crypto | E113: Wanchun Cui | F113: =452.91-10000.9 -> -9547.99 | G113: =452.91-10000.9 -> -9547.99 | H113: =H112+F113 -> 924732.3 | I113: =I112+G113 -> 925110.6
A114: 121 | B114: 46108 | C114: RTX | D114: Equities | E114: Wanchun Cui | F114: -200.4 | G114: -200.4 | H114: =H113+F114 -> 924531.9 | I114: =I113+G114 -> 924910.2
A115: 122 | B115: 46108 | C115: Occidental | D115: Equities | E115: Wanchun Cui | F115: 169.64 | G115: 169.64 | H115: =H114+F115 -> 924701.54 | I115: =I114+G115 -> 925079.84
A116: 123 | B116: 46108 | C116: regul | D116: Equities | E116: Yannis Khalfi | F116: =H115-H116 -> 17.46 | G116: =I115-I116 -> 395.76 | H116: 924684.08 | I116: 924684.08
B117: 46063.012 | C117: Kraft Heinz Foods - 6.500% - Feb 2040 | D117: Fixed Income | F117: 522.84 | G117: 522.84 | H117: =H115+F117 -> 925224.38 | I117: =I115+G117 -> 925602.68 | J117: KRAFT
B118: 46069.015 | C118: BUND 1.250% 15-Nov-2048 | D118: Fixed Income | F118: 137.5 | G118: 137.5 | H118: =H117+F118 -> 925361.88 | I118: =I117+G118 -> 925740.18 | J118: BUUND 1.250%
B119: 46083.011 | C119: United States Steel Corp - 6.875% - Mar 2029 | D119: Fixed Income | F119: 290.84 | G119: 290.84 | H119: =H118+F119 -> 925652.72 | I119: =I118+G119 -> 926031.02 | J119: United states
B120: 46083.012 | C120: BTP 3.100% 03-Jan-2040 | D120: Fixed Income | F120: 232.5 | G120: 232.5 | H120: =H119+F120 -> 925885.22 | I120: =I119+G120 -> 926263.52 | J120: BTP 3.10
B121: 46085.25 | C121: Dividends | D121: Equities | F121: 4.34 | G121: 4.34 | H121: =H120+F121 -> 925889.56 | I121: =I120+G121 -> 926267.86 | J121: PayPal Holdings...
B122: 46085.25 | C122: Dividends | D122: Equities | F122: 25.54 | G122: 25.54 | H122: =H121+F122 -> 925915.1 | I122: =I121+G122 -> 926293.4 | J122: Fox Corporation..
B123: 46085.25 | C123: Dividends | D123: Equities | F123: 12.31 | G123: 12.31 | H123: =H122+F123 -> 925927.41 | I123: =I122+G123 -> 926305.71 | J123: Lam Research Co...
B124: 46085.25 | C124: Dividends | D124: Equities | F124: 44.36 | G124: 44.36 | H124: =H123+F124 -> 925971.77 | I124: =I123+G124 -> 926350.07 | J124: Qualcomm, Inc.
B125: 46087.25 | C125: Dividends | D125: Equities | F125: 280.85 | G125: 280.85 | H125: =H124+F125 -> 926252.62 | I125: =I124+G125 -> 926630.92 | J125: Kraft Heinz Co
B126: 46087.25 | C126: Dividends | D126: Equities | F126: 35.79 | G126: 35.79 | H126: =H125+F126 -> 926288.41 | I126: =I125+G126 -> 926666.71 | J126: EBay Inc.
B127: 46090.208 | C127: Dividends | D127: Equities | F127: 3.1 | G127: 3.1 | H127: =H126+F127 -> 926291.51 | I127: =I126+G127 -> 926669.81 | J127: Alphabet Inc -
B128: 46094.208 | C128: Dividends | D128: Equities | F128: 82.33 | G128: 82.33 | H128: =H127+F128 -> 926373.84 | I128: =I127+G128 -> 926752.14 | J128: Xcel Energy, In...
B129: 46097.208 | C129: Dividends | D129: Equities | F129: 1.01 | G129: 1.01 | H129: =H128+F129 -> 926374.85 | I129: =I128+G129 -> 926753.15 | J129: NetEase Inc -
B130: 46104.208 | C130: Dividends | D130: ETF | F130: -253.83 | G130: -253.83 | H130: =H129+F130 -> 926121.02 | I130: =I129+G130 -> 926499.32 | J130: Invesco Capital

Sheet Bonds
A1: Issuer | B1: Country | C1: Bond Type | D1: Industry | E1: Coupon (%) | F1: Maturity | G1: Tenor | H1: Yield Style | I1: Notes | K1: Issuer | L1: (Tous)
A2: 21st Century Fox Amer Inc | B2: US | C2: Corporate | D2: Media | E2: 6.65 | F2: 13820 | G2: Long | H2: High | I2: Media company | K2: Bond Type | L2: (Tous) | M2: YOU ARE AMAZING, Good luck ! by Yannis
A3: 21st Century Fox Amer Inc | B3: US | C3: Corporate | D3: Media | E3: 6.4 | F3: 13119 | G3: Long | H3: High | I3: Media company
A4: 7-Eleven Inc | B4: US | C4: Corporate | D4: Retail | E4: 1.3 | F4: 46081 | G4: Short | H4: Low | I4: Convenience retail | K4: Country
A5: 7-Eleven Inc | B5: US | C5: Corporate | D5: Retail | E5: 2.5 | F5: 15008 | G5: Long | H5: Low | I5: Convenience retail | K5: France
A6: Apple Inc | B6: US | C6: Corporate | D6: Technology | E6: 3.25 | F6: 46079 | G6: Short | H6: Medium | I6: Large tech | K6: Germany
A7: Apple Inc | B7: US | C7: Corporate | D7: Technology | E7: 3.25 | F7: 46263 | G7: Medium | H7: Medium | I7: Large tech | K7: Italy
A8: Apple Inc | B8: US | C8: Corporate | D8: Technology | E8: 1.7 | F8: 46265 | G8: Medium | H8: Low | I8: Large tech | K8: Netherlands
A9: Abbott Labs | B9: US | C9: Corporate | D9: Healthcare | E9: 6 | F9: 14336 | G9: Long | H9: High | I9: Healthcare | K9: UK
A10: Abbott Labs | B10: US | C10: Corporate | D10: Healthcare | E10: 4.75 | F10: 15797 | G10: Long | H10: Medium | I10: Healthcare | K10: US
A11: AbbVie Inc | B11: US | C11: Corporate | D11: Healthcare | E11: 4.4 | F11: 15646 | G11: Long | H11: Medium | I11: Pharma | K11: Total général
A12: Adobe Inc | B12: US | C12: Corporate | D12: Technology | E12: 2.3 | F12: 10990 | G12: Medium | H12: Low | I12: Software
A13: Advanced Micro Devices Inc | B13: US | C13: Corporate | D13: Technology | E13: 3.924 | F13: 11841 | G13: Medium | H13: Medium | I13: Semiconductors
A14: Advanced Micro Devices Inc | B14: US | C14: Corporate | D14: Technology | E14: 4.393 | F14: 19146 | G14: Very Long | H14: Medium | I14: Semiconductors
A15: Alphabet Inc | B15: US | C15: Corporate | D15: Technology | E15: 1.1 | F15: 46264 | G15: Medium | H15: Low | I15: Internet services
A16: Alphabet Inc | B16: US | C16: Corporate | D16: Technology | E16: 1.9 | F16: 14824 | G16: Long | H16: Low | I16: Internet services
A17: Allstate Corp | B17: US | C17: Corporate | D17: Insurance | E17: 7.526 | F17: 19572 | G17: Very Long | H17: High | I17: Insurance
A18: Altria Group Inc | B18: US | C18: Corporate | D18: Consumer Staples | E18: 10.2 | F18: 14277 | G18: Long | H18: High | I18: Tobacco
A19: Altria Group Inc | B19: US | C19: Corporate | D19: Consumer Staples | E19: 9.95 | F19: 14185 | G19: Long | H19: High | I19: Tobacco
A20: Altria Group Inc | B20: US | C20: Corporate | D20: Consumer Staples | E20: 5.375 | F20: 16072 | G20: Long | H20: Medium | I20: Tobacco
A21: Alcan Inc | B21: US | C21: Corporate | D21: Materials | E21: 7.25 | F21: 46354 | G21: Short | H21: High | I21: Aluminum
A22: Avangrid Inc | B22: US | C22: Corporate | D22: Utilities | E22: 3.8 | F22: 46202 | G22: Medium | H22: Low | I22: Utilities
A23: Aflac Inc | B23: US | C23: Corporate | D23: Insurance | E23: 6.9 | F23: 14580 | G23: Long | H23: High | I23: Insurance
... A105: US Treasury | B105: US | C105: Government | D105: Government | E105: 4.25 | F105: 14380 | G105: Long | H105: Medium | I105: Long duration
A106: US Treasury | B106: US | C106: Government | D106: Government
A107: 3i Group | B107: UK | C107: Corporate | D107: Financials | E107: 5.75 | F107: 12024 | G107: Medium | H107: Medium | I107: Private equity group
A108: 3i Group | B108: UK | C108: Corporate | D108: Financials | E108: 3.75 | F108: 14763 | G108: Long | H108: Low | I108: Private equity group
A109: Aviva PLC | B109: UK | C109: Corporate | D109: Insurance | E109: 6.125 | F109: 13455 | G109: Long | H109: Medium | I109: Insurance
A110: Aviva PLC | B110: UK | C110: Corporate | D110: Insurance | E110: 4.375 | F110: 18142 | G110: Very Long | H110: Medium | I110: Insurance
A111: BP PLC | B111: UK | C111: Corporate | D111: Energy | E111: 5.773 | F111: 14001 | G111: Long | H111: Medium | I111: Oil & gas
A112: British Telecom PLC | B112: UK | C112: Corporate | D112: Communications | E112: 5.75 | F112: 46384 | G112: Short | H112: Medium | I112: Telecom
A113: British Telecom PLC | B113: UK | C113: Corporate | D113: Communications | E113: 3.125 | F113: 11628 | G113: Medium | H113: Low | I113: Telecom
A114: British Telecom PLC | B114: UK | C114: Corporate | D114: Communications | E114: 6.375 | F114: 13667 | G114: Long | H114: Medium | I114: Telecom
A115: Burberry Group | B115: UK | C115: Corporate | D115: Consumer Discretionary | E115: 5.75 | F115: 46203 | G115: Medium | H115: Medium | I115: Luxury retail
A116: HSBC Holdings PLC | B116: UK | C116: Corporate | D116: Financials | E116: 5.375 | F116: 46356 | G116: Medium | H116: Medium | I116: Banking
A117: HSBC Holdings PLC | B117: UK | C117: Corporate | D117: Financials | E117: 6 | F117: 14671 | G117: Long | H117: Medium | I117: Banking
A118: Lloyds Banking Group | B118: UK | C118: Corporate | D118: Financials | E118: 2 | F118: 46140 | G118: Short | H118: Low | I118: Banking
... A205: Italian Treasury (BTP) | B205: Italy | C205: Government | D205: Government | E205: 4.75 | F205: 16080 | G205: Long | H205: Medium | I205: BTP

Sheet Bonds Strategy
A1: Investment Grade Allocation (75% = USD 1,500,000) | C1: 18 bonds | D1: 300000
B2: To systematically learn interest rate dynamics, duration effects, yield curve behavior, and sector credit spreads, while maintaining portfolio stability. | D2: YOU ARE AMAZING, Good luck ! by Yannis
B3: IG-1 | Government Bonds – Duration Lab
C4: 30% of total bonds = USD 600,000 Government bonds isolate interest rate risk from credit risk Long and medium duration bonds allow us to observe price sensitivity to rate movements 30% provides meaningful duration exposure without dominating the portfolio
B5: Bond | C5: Country | D5: Maturity | E5: Weight | F5: Amount | H5: Why this bond & this weight
B6: US Treasury 15-May-2040 | C6: US | D6: 2040 | E6: 0.1 | F6: 200000 | G6: =$D$1*E6 -> 30000 | H6: Very long duration; maximizes sensitivity to rate changes, ideal for learning convexity
B7: US Treasury 15-Feb-2031 | C7: US | D7: 2031 | E7: 0.08 | F7: 160000 | G7: =$D$1*E7 -> 24000 | H7: Medium duration benchmark; serves as reference point on the US curve
B8: German Bund 04-Jul-2040 | C8: Germany | D8: 2040 | E8: 0.06 | F8: 120000 | G8: =$D$1*E8 -> 18000 | H8: Core EUR risk-free asset; allows comparison between USD and EUR rate dynamics
B9: French OAT 25-May-2043 | C9: France | D9: 2043 | E9: 0.06 | F9: 120000 | G9: =$D$1*E9 -> 18000 | H9: Slightly higher sovereign spread vs Bund; used to study sovereign risk premium
B11: IG-2 | Investment-Grade Corporates – Sector Comparison
C12: 30% of total bonds = USD 600,000 Same credit quality, different industries Allows analysis of sector-specific credit spreads Balanced exposure across defensive and cyclical sectors
B13: Bond | C13: Sector | D13: Maturity | E13: Weight | F13: Amount | H13: Why this bond & this weight
B14: Apple Inc 3.25% Feb-2026 | C14: Technology | D14: 2026 | E14: 0.06 | F14: 120000 | H14: Ultra-high-quality IG; acts as quasi risk-free corporate benchmark
B15: Microsoft Corp 5.20% Jun-2039 | C15: Technology | D15: 2039 | E15: 0.06 | F15: 120000 | H15: Long-term IG tech; combines duration risk with strong fundamentals
B16: Johnson & Johnson 4.95% May-2033 | C16: Healthcare | D16: 2033 | E16: 0.06 | F16: 120000 | H16: Defensive cash flows; low cyclicality
B17: JPMorgan Chase 5.50% Oct-2040 | C17: Financials | D17: 2040 | E17: 0.06 | F17: 120000 | H17: Financial sector exposure; sensitive to economic and rate cycles
B18: Enel Finance Intl 3.875% Mar-2029 | C18: Utilities | D18: 2029 | E18: 0.06 | F18: 120000 | H18: Stable regulated cash flows; lower spread volatility
B20: IG-3 | IG Curve & Geography
C21: 15% of total bonds = USD 300,000 Compare EUR vs USD investment-grade credit Same tenor, different countries and sectors Smaller allocation as this is a comparative, not core, experiment
B22: Bond | C22: Country | D22: Maturity | E22: Weight | F22: Amount | H22: Why this bond & this weight
B23: AXA S.A. 3.25% May-2029 | C23: France | D23: 2029 | E23: 0.05 | F23: 100000 | H23: European insurance IG; financial sector in EUR
B24: Deutsche Telekom 1.75% Mar-2031 | C24: Germany | D24: 2031 | E24: 0.05 | F24: 100000 | H24: Core European telecom; low-risk EUR corporate
B25: Nestlé / Danone equivalent | C25: Europe | D25: 2029 | E25: 0.05 | F25: 100000 | H25: Defensive consumer exposure; stable margins
A27: High Yield Allocation (25% = USD 500,000)
B28: To observe how credit risk is priced, repriced, and amplified, while strictly limiting downside risk.
B29: HY-1 | Fallen Angels / Near-IG
C30: 40% of HY = USD 200,000 Former IG issuers provide a clean view of downgrade risk Often show spread compression if fundamentals stabilize
B31: Bond | C31: Sector | D31: Maturity | E31: Weight | F31: Amount | H31: Why this bond & this weight
B32: Ford Motor 7.5% Aug-2026 | C32: Industrials | D32: 2026 | E32: 0.1 | F32: 200000 | H32: Classic fallen angel; short maturity limits risk while allowing spread recovery analysis
B34: HY-2 | Cyclical High Yield
C35: 35% of HY = USD 175,000 Credit risk strongly linked to economic cycles Allows observation of macro → cash flow → credit spread transmission
B36: Bond | C36: Sector | D36: Maturity | E36: Weight | F36: Amount | H36: Why this bond & this weight
B37: ENI S.p.A. 4.25% May-2033 | C37: Energy | D37: 2033 | E37: 0.09 | F37: 180000 | H37: Commodity-linked cash flows; credit sensitive to oil prices
B38: Boeing 6.875% Oct-2043 | C38: Industrials | D38: 2043 | E38: 0.08 | F38: 160000 | H38: High leverage and long maturity; strong credit cyclicality
B40: HY-3 | Stable Cash Flow High Yield
C41: 5% of HY = USD 125,000 High leverage but predictable cash flows Shows why markets demand high spreads even for stable businesses
B42: Bond | C42: Sector | D42: Maturity | E42: Weight | F42: Amount | H42: Why this bond & this weight
B43: Altria Group 9.95% Nov-2038 | C43: Consumer Staples | D43: 2038 | E43: 0.06 | F43: 120000 | H43: Very high coupon; stable tobacco cash flows
B44: Philip Morris 6.375% May-2038 | C44: Consumer Staples | D44: 2038 | E44: 0.06 | F44: 120000 | H44: Defensive HY; strong pricing power
A50: Bonds Strategy Version 2
A51: Class | B51: Semi-class | C51: Asset | D51: Ticker | E51: Total Amount (€) | F51: Currency | G51: Face value ($) | H51: Last Price ($) | I51: Last Coupon | J51: Accrued Interest Day | K51: Estimated Order + Accrued Interest ($) | L51: Estimated Order + Accrued Interest (€) | M51: Amount | N51: Actual ANumber | O51: Actual Amount ($) | P51: Actual Amount (€) | Q51: Short Note | R51: Note | S51: Investment Rationale | T51: What to Monitor | U51: Rebalancing / Exit Trigger | V51: What You Learn
A52: Long Duration Government & IG (40% = €120,000) | B52: Ultra-Long Sovereign Duration (20% = €60,000) | C52: US Treasury 2048 | D52: T-BOND 3.125% 15-May-2048 B-T-3.125-15052048 | E52: 30000 | F52: USD | G52: 1000 | H52: 754.66 | I52: 45976 | J52: 6.93 | K52: 761.59 | L52: 647.2 | M52: 46.353523 | N52: 46 | O52: 34714.36 | P52: 29771.2 | Q52: Bought US Treasury 3.125% May 2048 to gain high duration exposure and benefit from potential long-end yield declines. Large position reflects focus on price appreciation rather than carry. Trade driven by macro rate expectations and will be actively monitored and managed. | R52: US Treasury 3.125% 15-May-2048 Ticker: B-T-3.125-15052048 Investment Thesis Long ultra-long US Treasury to gain maximum duration and convexity exposure Macro-driven trade expecting long-end yields to decline Role in Portfolio Core duration hedge and convexity anchor Offsets credit, equity-linked, and cyclical risk elsewhere in portfolio Sizing Logic $30,000 reflects deliberate overweight to long-duration rates Focus on price sensitivity (Mod. Duration ~46), not carry Expected Return Sources Capital gains from long-end yield compression Convexity upside in recession or risk-off scenarios Key Risks & Monitoring Risk: inflation persistence or rising term premium Monitor US 30Y yields, breakevens, Fed policy signals; actively rebalance if regime shifts | S52: • Long-end duration & convexity play • Macro recession / rate-cut hedge • Focus on price appreciation over carry | T52: • US 20Y–30Y Treasury yields • Fed pivot signals • Inflation expectations (breakevens) | U52: • Take profit after sharp long-end rally • Cut if yields structurally reprice higher | V52: • How ultra-long sovereigns amplify macro rate views
C53: German Bund 2048 | D53: BUND 1.250% 15-Nov-2048 DE-B-1.250-15112048 | E53: 15000 | F53: EUR | G53: 1000 | H53: 656.8 | I53: 45884 | J53: 5.92 | K53: 662.72 | L53: 663.02 | M53: 22.623752 | N53: 22 | O53: 14449.6 | P53: 14586.44 | Q53: Initiating ultra-long German Bund for EUR risk-free duration and convexity. Positioned for ECB easing, growth slowdown, and risk-off scenarios. Complements US Treasury exposure and enhances cross-currency sovereign diversification. Returns driven by yield compression, not carry. | R53: German Bund 1.250% 15-Nov-2048 Investment Thesis Core EUR ultra-long sovereign duration exposure Beneficiary of ECB easing cycle and long-end rate compression Role in Portfolio EUR risk-free duration anchor Balances credit and USD exposure Sizing Logic €15k as half-size relative to US Treasury due to lower yield/convexity Expected Return Capital gains from long-end yield decline Convexity in recession / risk-off scenarios Monitoring ECB policy path, EUR inflation expectations, 30Y Bund yield | S53: • Core EUR risk-free duration anchor • Deflation / risk-off hedge • Low credit risk stabilizer | T53: • ECB policy path • Germany growth & inflation • EUR rates curve shape | U53: • Reduce if ECB turns structurally hawkish • Trim if Bunds richen excessively | V53: • How core sovereigns behave in EUR stress regimes
C54: French OAT 2045 | D54: OAT 3.250% 25-May-2045 FR-O-3.250-25052045 | E54: 15000 | F54: EUR | G54: 1000 | H54: 886.65 | I54: 45986 | J54: 6.32 | K54: 892.97 | L54: 893.22 | M54: 16.793175 | N54: 16 | O54: 14186.4 | P54: 14291.52 | Q54: Adding ultra-long French OAT for Eurozone duration and convexity. Positioned for ECB easing and growth slowdown. Offers yield pickup versus Bunds while maintaining core sovereign risk profile. Complements German and US long-duration exposure. | R54: French OAT 3.250% 25-May-2045 Investment Thesis Long EUR duration with positive carry vs Bund Capture term premium in semi-core sovereign Role in Portfolio Yield-enhanced EUR duration Diversifies pure core-Bund exposure Sizing Logic €15k symmetric allocation vs Bund Expected Return Carry + moderate spread tightening vs Germany Monitoring OAT-Bund spread, French fiscal signals | S54: • EUR duration with mild spread pickup vs Bund • Balanced carry + duration exposure | T54: • OAT–Bund spread • French fiscal / political risk • ECB reinvestment policy | U54: • Exit if OAT–Bund spread widens structurally • Trim after spread compression | V54: • Sovereign spread risk within core Europe
B55: Long-Dated Investment-Grade Tech (20% = €60,000) | C55: Microsoft 2039 | D55: Microsoft Corp - 5.2% - Jun 2039 B-MSFT-5.2-01062039 | E55: 21000 | F55: USD | G55: 1000 | H55: 1044.08 | I55: 45992 | J55: 9.26 | K55: 1053.34 | L55: 894.47 | M55: 23.47759 | N55: 23 | O55: 24013.84 | P55: 20572.81 | Q55: Long MSFT 2039 for rate-cut convexity and carry. Premium justified by high coupon vs market yield; benefit from long-end yield compression. | R55: Microsoft 2039 — €21,000（7%） Investment Thesis High-quality IG credit combining strong balance sheet, recurring cash flows, and meaningful long-duration exposure. Role in Portfolio Long-duration IG credit stabilizer with lower default and downgrade risk. Sizing Logic Core IG exposure sized larger than other corporates due to superior credit quality and liquidity. Expected Return Sources Coupon carry Spread stability or modest tightening Rate-driven price appreciation Key Risks & Mitigants Risk: Valuation compression if tech spreads widen Mitigant: Paired with sovereign duration and non-tech IG exposure Monitoring & Exit Triggers Net debt / EBITDA trends Regulatory pressure on big tech Reduce if leverage policy materially changes | S55: • High-quality IG tech credit • Long-duration rate convexity with strong balance sheet • Defensive growth exposure | T55: • Long-end US yields • MSFT credit spread • Tech capex cycle | U55: • Trim if spreads fully compress • Exit if tech credit fundamentals weaken | V55: • Difference between rate-driven vs credit-driven returns
C56: Apple 2041 | D56: Apple Inc - 1.700% - Aug 2031 B-APPL-1.700-05082031 | E56: 21000 | F56: USD | G56: 1000 | H56: 887.61 | I56: 46058 | J56: -0.06 | K56: 887.55 | L56: 753.69 | M56: 27.862914 | N56: 27 | O56: 23965.47 | P56: 20349.63 | Q56: Buy Apple 2031 as a low-coupon IG bond with high duration. Positioned to benefit from potential rate cuts; strong balance sheet limits credit risk. | R56: Apple 1.700% Aug-2031 Investment Thesis Ultra-high-quality IG with minimal default risk Duration exposure with defensive profile Role in Portfolio Stability anchor within credit sleeve Sizing Logic $21k balanced vs Microsoft Expected Return Price sensitivity to rates, not credit Monitoring Rate environment, Apple balance sheet strength | S56: • Ultra-high-quality issuer • Low-coupon = high rate sensitivity • Pure duration exposure via corporate IG | T56: • US yield curve • Apple cash flow & capital returns • IG tech spread levels | U56: • Rebalance if duration overweight • Exit if curve steepens sharply | V56: • How low coupons magnify duration risk
C57: ASML 2032 | D57: ASML Holding - 2.250% - May 2032 NL-ASML-2.250-17042032 | E57: 18000 | F57: EUR | G57: 1000 | H57: 966.33 | I57: 45978 | J57: 4.87 | K57: 971.2 | L57: 973.11 | M57: 18.497395 | N57: 18 | O57: 17393.94 | P57: 17515.98 | Q57: Long ASML 2.25% May-2032 to gain high-quality tech IG exposure with moderate duration. Trade focuses on spread stability and rate sensitivity, supported by ASML’s monopoly-like industry position and strong balance sheet. | R57: ASML 2.250% May-2032 Investment Thesis Strategic semiconductor monopoly credit Strong pricing power and structural demand Role in Portfolio Cyclical IG tech diversifier Sizing Logic €18k due to shorter tenor and EUR exposure Expected Return Carry + credit spread stability Monitoring Semiconductor cycle, geopolitics | S57: • Strategic semiconductor monopoly • IG tech with moderate duration • EUR tech exposure diversifier | T57: • Semiconductor cycle • Capex by foundries • ASML backlog visibility | U57: • Trim if chip cycle peaks • Add on spread widening without credit deterioration | V57: • Credit behavior of monopoly-like tech issuers
A58: High Yield Credit (30% = €90,000) | B58: Fallen Angels / Near-IG HY (12% = €36,000) | C58: Ford 2026 | D58: Ford Motor Co. - 7.500% - Aug 2026 B-F-7.500-01082026 | E58: 18000 | F58: USD | G58: 1000 | H58: 1015.5 | I58: 46054 | J58: 0.62 | K58: 1016.12 | L58: 862.86 | M58: 20.860858 | N58: 20 | O58: 20310 | P58: 17257.2 | Q58: Long Ford 7.5% Aug-2026 for short-dated high-carry credit exposure. Trade focuses on yield capture and pull-to-par with limited duration risk, supported by near-term maturity and manageable refinancing profile. | R58: Ford 7.500% Aug-2026 Investment Thesis Fallen angel HY with near-term maturity High carry with refinancing optionality Role in Portfolio Short-dated HY carry play Sizing Logic $18k limited tenor risk Expected Return Coupon income + pull-to-par Monitoring Auto demand, refinancing progress | S58: • Fallen angel rebound trade • Short-dated HY with strong cash generation • Yield-driven carry play | T58: • Auto demand • Liquidity & refinancing risk • Rating trajectory | U58: • Exit near maturity • Cut if liquidity deteriorates | V58: • Risk/return profile of short-dated HY
C59: Kraft Heinz 2040 | D59: Kraft Heinz Foods - 6.500% - Feb 2040 B-KRFT-6.5-09022040 | E59: 18000 | F59: USD | G59: 1000 | H59: 1079.59 | I59: 45878 | J59: 31.88 | K59: 1111.47 | L59: 943.82 | M59: 19.071433 | N59: 19 | O59: 20512.21 | P59: 17932.58 | Q59: LKraft Heinz 6.5% Feb-2040 Long to capture high coupon carry and defensive consumer-staples credit exposure. Position targets income-driven returns with moderate duration sensitivity, supported by resilient cash flows and non-cyclical demand. | R59: Kraft Heinz 6.500% Feb-2040 Investment Thesis Defensive consumer staples HY Stable cash flows support long-dated debt Role in Portfolio HY income stabilizer Sizing Logic $18k symmetric with Ford Expected Return High carry + gradual spread normalization Monitoring Leverage metrics, pricing power | S59: • Stable consumer staples cash flows • HY carry with defensive characteristics • Long-dated income play | T59: • Leverage trends • Margin stabilization • Consumer demand | U59: • Trim if leverage worsens • Exit if spreads tighten excessively | V59: • Defensive HY behavior across cycles
B60: Stable Cash-Flow HY (10% = €30,000) | C60: Altria 2038 | D60: Altria Group Inc - 9.95% - Nov 2038 B-MO-9.95-10112038 | E60: 15000 | F60: USD | G60: 1000 | H60: 1366.1 | I60: 45971 | J60: 23.44 | K60: 1389.54 | L60: 1179.96 | M60: 12.712295 | N60: 12 | O60: 16393.2 | P60: 14159.52 | Q60: High-carry defensive credit. Locking ~10% coupon from stable cash-flow issuer to anchor portfolio yield and offset rate/tech volatility. | R60: Altria 9.95% Nov-2038 Investment Thesis Very high cash-flow tobacco credit Regulatory risk priced into yield Role in Portfolio Core HY income engine Sizing Logic $15k due to regulatory tail risk Expected Return Coupon-driven total return Monitoring Regulation, payout sustainability | S60: • Very high cash-flow visibility • High coupon income • Defensive sin-sector HY | T60: • Regulatory risk • Volume trends • Litigation developments | U60: • Take profit after spread compression • Exit on regulatory shock | V60: • Pricing power vs regulatory risk trade-off
C61: Philip Morris 2038 | D61: Philip Morris - 6.375% - May 2038 B-PM-6.375-16052038 | E61: 15000 | F61: USD | G61: 1000 | H61: 1112.83 | I61: 45977 | J61: 13.97 | K61: 1126.8 | L61: 956.85 | M61: 15.676438 | N61: 15 | O61: 16692.45 | P61: 14352.75 | Q61: High-carry defensive credit. Stable global tobacco cash flows support attractive income and portfolio yield stabilization. | R61: Philip Morris 6.375% May-2038 Investment Thesis Global tobacco with diversification vs Altria Lower regulatory concentration risk Role in Portfolio Complementary HY cash-flow exposure Sizing Logic $15k paired with Altria Expected Return Carry + credit stability Monitoring Reduced-risk product transition | S61: • Global diversification vs Altria • Strong cash flows • HY with lower regulatory concentration risk | T61: • Heated tobacco adoption • FX exposure • Credit metrics | U61: • Rebalance vs Altria if relative value shifts | V61: • Intra-sector relative value within tobacco
B62: Event / Cyclical HY (8% = €24,000) | C62: Boeing 2043 | D62: Boeing Co - 6.875% - Oct 2043 B-BA-6.875-15102043 | E62: 15000 | F62: USD | G62: 1000 | H62: 1080 | I62: 45945 | J62: 21.1 | K62: 1101.1 | L62: 943.51 | M62: 15.898083 | N62: 15 | O62: 16200 | P62: 14152.65 | Q62: Cyclical recovery credit with elevated carry. Position targets spread compression as Boeing normalizes operations and cash flow over the cycle. | R62: Boeing 2043 — €15,000（5%） Investment Thesis Event-driven high yield exposure linked to operational normalization and delivery recovery. Role in Portfolio Return enhancer with asymmetric upside from credit spread compression. Sizing Logic Capped at 5% due to idiosyncratic operational and regulatory risks. Expected Return Sources High coupon carry Spread tightening upon resolution of production and safety issues Key Risks & Mitigants Risk: New safety incidents or delivery halts Mitigant: Limited sizing and diversification across HY bucket Monitoring & Exit Triggers FAA approvals Aircraft delivery schedules Exit if operational setbacks re-emerge | S62: • Event-driven HY credit • Recovery upside from aerospace normalization • High carry compensation | T62: • Aircraft deliveries • Free cash flow • Rating outlook | U62: • Exit if recovery stalls • Trim after major credit upgrade | V62: • Event risk vs carry in cyclical credits
C63: US Steel 2029 | D63: United States Steel Corp - 6.875% - Mar 2029 B-X-6.875-01032029 | E63: 9000 | F63: USD | G63: 1000 | H63: 1004.57 | I63: 45901 | J63: 29.38 | K63: 1033.95 | L63: 878 | M63: 10.250569 | N63: 10 | O63: 10045.7 | P63: 8780 | Q63: Short-dated cyclical credit capturing high carry with limited duration risk. Trade targets stable income and near-term spread normalization into 2029 maturity. | R63: US Steel 6.875% Mar-2029 Investment Thesis Short-dated cyclical commodity credit High carry with limited duration risk Role in Portfolio Tactical HY cycle exposure Sizing Logic $9k small satellite position Expected Return Carry + pull-to-par Monitoring Steel prices, demand cycle | S63: • Late-cycle cyclical HY exposure • Shorter tenor limits downside • Commodity-linked rebound play | T63: • Steel prices • Global demand • Balance sheet discipline | U63: • Exit if cycle turns down • Hold to maturity if stable | V63: • Timing risk in commodity-linked credit
A64: Relative Value Strategies (20% = €60,000) | B64: Sovereign Spread Trade (10% = €30,000) | C64: BTP 2040 Long | D64: BTP 3.100% 03-Jan-2040 IT-B-3.100-03012040 | E64: 15000 | F64: EUR | G64: 1000 | H64: 925.86 | I64: 45901 | J64: 13.25 | K64: 939.11 | L64: 939.51 | M64: 15.965769 | N64: 15 | O64: 13887.9 | P64: 14092.65 | Q64: BTP 2040 Long to express ECB easing and Italy spread compression. High duration and clean rates/spread beta with manageable volatility over 2-month horizon. | R64: BTP 2040 Long — €15,000（5%） Investment Thesis Relative value trade expressing convergence between Italian sovereign spreads and core EUR rates under ECB backstop. Role in Portfolio Spread trade rather than pure duration exposure. Sizing Logic Matched against Bund hedge to isolate spread movement. Expected Return Sources BTP–Bund spread compression Carry advantage vs core sovereigns Key Risks & Mitigants Risk: Italian fiscal slippage or political shock Mitigant: Bund hedge neutralizes rate risk Monitoring & Exit Triggers BTP–Bund spread levels Italian budget announcements ECB transmission protection signals | S64: • Peripheral sovereign spread compression play • Long Italy duration • ECB backstop exposure | T64: • BTP–Bund spread • Italian fiscal policy • ECB support stance | U64: • Exit if political risk escalates • Take profit on spread tightening | V64: • Sovereign spread dynamics in EUR
C65: Bund 2040 Short / Hedge | D65: BUND 4.750% 04-Jul-2040 DE-B-4.750-04072040 | E65: 15000 | F65: EUR | G65: 1000 | H65: 1184.56 | I65: 46026 | J65: 4.03 | K65: 1188.59 | L65: 1189.1 | M65: 12.614582 | N65: 12 | O65: 14214.72 | P65: 14269.2 | Q65: Bund 2040 Short as duration hedge against long BTP/OAT. Neutralizes pure rate risk while retaining peripheral spread compression exposure. | R65: Bund 4.750% Jul-2040 (Short / Hedge) Investment Thesis Hedge against EUR rate rise Neutralizes duration in BTP leg Role in Portfolio Relative-value hedge leg Sizing Logic €15k matched notional Expected Return Relative performance vs BTP Monitoring BTP-Bund spread dynamics | S65: • Hedge against BTP spread widening • Duration-neutral EUR RV trade • Risk-off protection leg | T65: • Bund yields • ECB communication • BTP volatility | U65: • Adjust hedge ratio if spreads compress materially | V65: • How sovereign hedges work in RV trades
B66: Credit Relative Value (10% = €30,000) | C66: JPM 2038 | D66: JP Morgan Chase Co - 6.400% - May 2038 B-JPM-6.4-15052038 | E66: 10000 | F66: USD | G66: 1000 | H66: 1152.58 | I66: 45976 | J66: 14.2 | K66: 1166.78 | L66: 990.8 | M66: 10.092854 | N66: 10 | O66: 11525.8 | P66: 9908 | Q66: Long JPM 6.4% May-2038 as a credit relative value anchor. High coupon provides strong carry while long maturity offers duration exposure. Position expresses bank credit stability with limited idiosyncratic risk and benefits from spread compression or long-end yield declines. | R66: JPM 6.400% May-2038 Investment Thesis High-quality US bank credit Attractive yield vs peers Role in Portfolio Credit relative-value anchor Sizing Logic $10k core financial credit Expected Return Carry + modest spread tightening Monitoring Capital ratios, macro credit cycle | S66: • Systemic bank credit • High coupon IG/HY crossover • Financials RV anchor | T66: • Bank funding spreads • Yield curve shape • Regulatory capital ratios | U66: • Trim if spreads normalize fully • Exit on financial stress | V66: • Bank credit sensitivity to macro cycles
C67: JPM 2040 | D67: JP Morgan Chase Co - 5.500% - Oct 2040 B-JPM-5.5-15102040 | E67: 8000 | F67: USD | G67: 1000 | H67: 1041.4 | I67: 45945 | J67: 16.88 | K67: 1058.28 | L67: 898.66 | M67: 8.9021432 | N67: 8 | O67: 8331.2 | P67: 7189.28 | Q67: Long JPM 5.5% Oct-2040 to extend bank credit duration with stable carry. Position targets long-end rate sensitivity and potential credit spread tightening while maintaining exposure to a high-quality global systemically important bank. | R67: JPM 5.500% Oct-2040 Investment Thesis Longer-duration extension of JPM credit Higher rate sensitivity Role in Portfolio Curve steepness exposure within issuer Sizing Logic $8k smaller size due to duration Expected Return Carry + curve-driven price gains Monitoring Long-end rates, bank regulation | S67: • Longer-duration financial credit • Curve & spread relative value vs JPM 2038 • Carry + duration mix | T67: • Long-end rates • Bank term funding costs • Credit curve slope | U67: • Switch to shorter tenor if curve steepens | V67: • Credit curve positioning within one issuer
C68: Sanofi 2038 | D68: Sanofi S.A - 1.875% - Mar 2038 FR-SNY-1.875-21032038 | E68: 7000 | F68: EUR | G68: 1000 | H68: 838.91 | I68: 45921 | J68: 6.99 | K68: 845.9 | L68: 849.84 | M68: 8.2368446 | N68: 8 | O68: 6711.28 | P68: 6798.72 | Q68: Non-financial IG anchor in Credit RV bucket. Defensive pharma cash flows with low beta. Used as spread benchmark versus bank credit to isolate financial sector-specific spread moves. | R68: Sanofi 1.875% Mar-2038 Investment Thesis Defensive healthcare IG Stable earnings and low cyclicality Role in Portfolio Non-tech IG diversifier Sizing Logic €7k satellite allocation Expected Return Duration + stability premium Monitoring Pipeline, regulatory updates | S68: • Defensive healthcare IG • Low business cyclicality • EUR duration diversifier | T68: • Drug pipeline updates • Litigation risk • EUR credit spreads | U68: • Trim if valuation richens • Exit on adverse clinical events | V68: • Stability of healthcare credit through cycles
C69: TotalEnergies 2039 | D69: TotalEnergies Capital Intl. - 1.535% - May 2039 FR-TTE-1.535-31052039 | E69: 5000 | F69: EUR | G69: 1000 | H69: 749.91 | I69: 45991 | J69: 2.78 | K69: 752.69 | L69: 755.78 | M69: 6.6156818 | N69: 6 | O69: 4499.46 | P69: 4534.68 | Q69: Non-financial IG energy credit added as macro-sensitive leg in Credit RV bucket. Provides diversification from tech and financials while linking portfolio to inflation and commodity dynamics. | R69: TotalEnergies 1.535% May-2039 Investment Thesis Integrated energy major with strong balance sheet Long-dated IG exposure Role in Portfolio Energy transition-linked IG credit Sizing Logic €5k small allocation due to low coupon Expected Return Rate-driven price appreciation Monitoring Energy prices, capex discipline | S69: • Energy major with strong FCF • Transition risk priced conservatively • Long-dated IG carry | T69: • Oil & gas prices • Energy transition capex • Credit leverage | U69: • Reduce if energy cycle peaks • Exit on leverage deterioration | V69: • Energy credit vs commodity volatility
A70: Tactical Cash (10% = €30,000) | E70: 30000 | R70: Tactical Cash — €30,000（10%） Investment Thesis Maintains optionality to exploit volatility-driven mispricings. Role in Portfolio Liquidity buffer and tactical deployment capital. Sizing Logic 10% ensures flexibility without diluting structural positions. Expected Return Sources Optionality rather than yield Monitoring & Exit Triggers Market stress events Forced selling in credit or rates markets | S70: Optionality & flexibility | U70: After CPI, Fed/ECB, spread shocks | V70: Liquidity as a portfolio tool
A73: Class | B73: Semi-class | C73: Asset | D73: Ticker | E73: Total Amount (€) | F73: Currency | G73: Face value ($) | H73: Last Price ($) | I73: Last Coupon | J73: Accrued Interest Day | K73: Estimated Order + Accrued Interest ($) | L73: Estimated Order + Accrued Interest (€) | M73: Amount | N73: Actual ANumber | O73: Actual Amount ($) | P73: Actual Amount (€) | Q73: Short Note | R73: Note | S73: Investment Rationale | T73: What to Monitor | U73: Rebalancing / Exit Trigger | V73: What You Learn
A74: Long Duration Government & IG (40% = €120,000) | B74: Ultra-Long Sovereign Duration (20% = €60,000) | C74: US Treasury 2048 | D74: T-BOND 3.125% 15-May-2048 B-T-3.125-15052048 | E74: 30000 | F74: USD | G74: 1000 | H74: 754.66 | I74: 45976 | J74: 6.93 | K74: 761.59 | L74: 647.2 | M74: 46.353523 | N74: 46 | O74: 34714.36 | P74: 29771.2 | Q74: Bought US Treasury 3.125% May 2048 to gain high duration exposure and benefit from potential long-end yield declines. Large position reflects focus on price appreciation rather than carry. Trade driven by macro rate expectations and will be actively monitored and managed. | R74: US Treasury 3.125% 15-May-2048 Ticker: B-T-3.125-15052048 Investment Thesis Long ultra-long US Treasury to gain maximum duration and convexity exposure Macro-driven trade expecting long-end yields to decline Role in Portfolio Core duration hedge and convexity anchor Offsets credit, equity-linked, and cyclical risk elsewhere in portfolio Sizing Logic $30,000 reflects deliberate overweight to long-duration rates Focus on price sensitivity (Mod. Duration ~46), not carry Expected Return Sources Capital gains from long-end yield compression Convexity upside in recession or risk-off scenarios Key Risks & Monitoring Risk: inflation persistence or rising term premium Monitor US 30Y yields, breakevens, Fed policy signals; actively rebalance if regime shifts | S74: • Long-end duration & convexity play • Macro recession / rate-cut hedge • Focus on price appreciation over carry | T74: • US 20Y–30Y Treasury yields • Fed pivot signals • Inflation expectations (breakevens) | U74: • Take profit after sharp long-end rally • Cut if yields structurally reprice higher | V74: • How ultra-long sovereigns amplify macro rate views
C75: German Bund 2048 | D75: BUND 1.250% 15-Nov-2048 DE-B-1.250-15112048 | E75: 15000 | F75: EUR | G75: 1000 | H75: 656.8 | I75: 45884 | J75: 5.92 | K75: 662.72 | L75: 663.02 | M75: 22.623752 | N75: 22 | O75: 14449.6 | P75: 14586.44 | Q75: Initiating ultra-long German Bund for EUR risk-free duration and convexity. Positioned for ECB easing, growth slowdown, and risk-off scenarios. Complements US Treasury exposure and enhances cross-currency sovereign diversification. Returns driven by yield compression, not carry. | R75: German Bund 1.250% 15-Nov-2048 Investment Thesis Core EUR ultra-long sovereign duration exposure Beneficiary of ECB easing cycle and long-end rate compression Role in Portfolio EUR risk-free duration anchor Balances credit and USD exposure Sizing Logic €15k as half-size relative to US Treasury due to lower yield/convexity Expected Return Capital gains from long-end yield decline Convexity in recession / risk-off scenarios Monitoring ECB policy path, EUR inflation expectations, 30Y Bund yield | S75: • Core EUR risk-free duration anchor • Deflation / risk-off hedge • Low credit risk stabilizer | T75: • ECB policy path • Germany growth & inflation • EUR rates curve shape | U75: • Reduce if ECB turns structurally hawkish • Trim if Bunds richen excessively | V75: • How core sovereigns behave in EUR stress regimes
C76: French OAT 2045 | D76: OAT 3.250% 25-May-2045 FR-O-3.250-25052045 | E76: 15000 | F76: EUR | G76: 1000 | H76: 886.65 | I76: 45986 | J76: 6.32 | K76: 892.97 | L76: 893.22 | M76: 16.793175 | N76: 16 | O76: 14186.4 | P76: 14291.52 | Q76: Adding ultra-long French OAT for Eurozone duration and convexity. Positioned for ECB easing and growth slowdown. Offers yield pickup versus Bunds while maintaining core sovereign risk profile. Complements German and US long-duration exposure. | R76: French OAT 3.250% 25-May-2045 Investment Thesis Long EUR duration with positive carry vs Bund Capture term premium in semi-core sovereign Role in Portfolio Yield-enhanced EUR duration Diversifies pure core-Bund exposure Sizing Logic €15k symmetric allocation vs Bund Expected Return Carry + moderate spread tightening vs Germany Monitoring OAT-Bund spread, French fiscal signals | S76: • EUR duration with mild spread pickup vs Bund • Balanced carry + duration exposure | T76: • OAT–Bund spread • French fiscal / political risk • ECB reinvestment policy | U76: • Exit if OAT–Bund spread widens structurally • Trim after spread compression | V76: • Sovereign spread risk within core Europe
B77: Long-Dated Investment-Grade Tech (20% = €60,000) | C77: Microsoft 2039 | D77: Microsoft Corp - 5.2% - Jun 2039 B-MSFT-5.2-01062039 | E77: 21000 | F77: USD | G77: 1000 | H77: 1044.08 | I77: 45992 | J77: 9.26 | K77: 1053.34 | L77: 894.47 | M77: 23.47759 | N77: 23 | O77: 24013.84 | P77: 20572.81 | Q77: Long MSFT 2039 for rate-cut convexity and carry. Premium justified by high coupon vs market yield; benefit from long-end yield compression. | R77: Microsoft 2039 — €21,000（7%） Investment Thesis High-quality IG credit combining strong balance sheet, recurring cash flows, and meaningful long-duration exposure. Role in Portfolio Long-duration IG credit stabilizer with lower default and downgrade risk. Sizing Logic Core IG exposure sized larger than other corporates due to superior credit quality and liquidity. Expected Return Sources Coupon carry Spread stability or modest tightening Rate-driven price appreciation Key Risks & Mitigants Risk: Valuation compression if tech spreads widen Mitigant: Paired with sovereign duration and non-tech IG exposure Monitoring & Exit Triggers Net debt / EBITDA trends Regulatory pressure on big tech Reduce if leverage policy materially changes | S77: • High-quality IG tech credit • Long-duration rate convexity with strong balance sheet • Defensive growth exposure | T77: • Long-end US yields • MSFT credit spread • Tech capex cycle | U77: • Trim if spreads fully compress • Exit if tech credit fundamentals weaken | V77: • Difference between rate-driven vs credit-driven returns
C78: Apple 2041 | D78: Apple Inc - 1.700% - Aug 2031 B-APPL-1.700-05082031 | E78: 21000 | F78: USD | G78: 1000 | H78: 887.61 | I78: 46058 | J78: -0.06 | K78: 887.55 | L78: 753.69 | M78: 27.862914 | N78: 27 | O78: 23965.47 | P78: 20349.63 | Q78: Buy Apple 2031 as a low-coupon IG bond with high duration. Positioned to benefit from potential rate cuts; strong balance sheet limits credit risk. | R78: Apple 1.700% Aug-2031 Investment Thesis Ultra-high-quality IG with minimal default risk Duration exposure with defensive profile Role in Portfolio Stability anchor within credit sleeve Sizing Logic $21k balanced vs Microsoft Expected Return Price sensitivity to rates, not credit Monitoring Rate environment, Apple balance sheet strength | S78: • Ultra-high-quality issuer • Low-coupon = high rate sensitivity • Pure duration exposure via corporate IG | T78: • US yield curve • Apple cash flow & capital returns • IG tech spread levels | U78: • Rebalance if duration overweight • Exit if curve steepens sharply | V78: • How low coupons magnify duration risk
C79: ASML 2032 | D79: ASML Holding - 2.250% - May 2032 NL-ASML-2.250-17042032 | E79: 18000 | F79: EUR | G79: 1000 | H79: 966.33 | I79: 45978 | J79: 4.87 | K79: 971.2 | L79: 973.11 | M79: 18.497395 | N79: 18 | O79: 17393.94 | P79: 17515.98 | Q79: Long ASML 2.25% May-2032 to gain high-quality tech IG exposure with moderate duration. Trade focuses on spread stability and rate sensitivity, supported by ASML’s monopoly-like industry position and strong balance sheet. | R79: ASML 2.250% May-2032 Investment Thesis Strategic semiconductor monopoly credit Strong pricing power and structural demand Role in Portfolio Cyclical IG tech diversifier Sizing Logic €18k due to shorter tenor and EUR exposure Expected Return Carry + credit spread stability Monitoring Semiconductor cycle, geopolitics | S79: • Strategic semiconductor monopoly • IG tech with moderate duration • EUR tech exposure diversifier | T79: • Semiconductor cycle • Capex by foundries • ASML backlog visibility | U79: • Trim if chip cycle peaks • Add on spread widening without credit deterioration | V79: • Credit behavior of monopoly-like tech issuers
A80: High Yield Credit (30% = €90,000) | B80: Fallen Angels / Near-IG HY (12% = €36,000) | C80: Ford 2026 | D80: Ford Motor Co. - 7.500% - Aug 2026 B-F-7.500-01082026 | E80: 18000 | F80: USD | G80: 1000 | H80: 1015.5 | I80: 46054 | J80: 0.62 | K80: 1016.12 | L80: 862.86 | M80: 20.860858 | N80: 20 | O80: 20310 | P80: 17257.2 | Q80: Long Ford 7.5% Aug-2026 for short-dated high-carry credit exposure. Trade focuses on yield capture and pull-to-par with limited duration risk, supported by near-term maturity and manageable refinancing profile. | R80: Ford 7.500% Aug-2026 Investment Thesis Fallen angel HY with near-term maturity High carry with refinancing optionality Role in Portfolio Short-dated HY carry play Sizing Logic $18k limited tenor risk Expected Return Coupon income + pull-to-par Monitoring Auto demand, refinancing progress | S80: • Fallen angel rebound trade • Short-dated HY with strong cash generation • Yield-driven carry play | T80: • Auto demand • Liquidity & refinancing risk • Rating trajectory | U80: • Exit near maturity • Cut if liquidity deteriorates | V80: • Risk/return profile of short-dated HY
C81: Kraft Heinz 2040 | D81: Kraft Heinz Foods - 6.500% - Feb 2040 B-KRFT-6.5-09022040 | E81: 18000 | F81: USD | G81: 1000 | H81: 1079.59 | I81: 45878 | J81: 31.88 | K81: 1111.47 | L81: 943.82 | M81: 19.071433 | N81: 19 | O81: 20512.21 | P81: 17932.58 | Q81: Long Kraft Heinz 6.5% Feb-2040 to capture high coupon carry and defensive consumer-staples credit exposure. Position targets income-driven returns with moderate duration sensitivity, supported by resilient cash flows and non-cyclical demand. | R81: Kraft Heinz 6.500% Feb-2040 Investment Thesis Defensive consumer staples HY Stable cash flows support long-dated debt Role in Portfolio HY income stabilizer Sizing Logic $18k symmetric with Ford Expected Return High carry + gradual spread normalization Monitoring Leverage metrics, pricing power | S81: • Stable consumer staples cash flows • HY carry with defensive characteristics • Long-dated income play | T81: • Leverage trends • Margin stabilization • Consumer demand | U81: • Trim if leverage worsens • Exit if spreads tighten excessively | V81: • Defensive HY behavior across cycles
B82: Stable Cash-Flow HY (10% = €30,000) | C82: Altria 2038 | D82: Altria Group Inc - 9.95% - Nov 2038 B-MO-9.95-10112038 | E82: 15000 | F82: USD | G82: 1000 | H82: 1366.1 | I82: 45971 | J82: 23.44 | K82: 1389.54 | L82: 1179.96 | M82: 12.712295 | N82: 12 | O82: 16393.2 | P82: 14159.52 | Q82: High-carry defensive credit. Locking ~10% coupon from stable cash-flow issuer to anchor portfolio yield and offset rate/tech volatility. | R82: Altria 9.95% Nov-2038 Investment Thesis Very high cash-flow tobacco credit Regulatory risk priced into yield Role in Portfolio Core HY income engine Sizing Logic $15k due to regulatory tail risk Expected Return Coupon-driven total return Monitoring Regulation, payout sustainability | S82: • Very high cash-flow visibility • High coupon income • Defensive sin-sector HY | T82: • Regulatory risk • Volume trends • Litigation developments | U82: • Take profit after spread compression • Exit on regulatory shock | V82: • Pricing power vs regulatory risk trade-off
C83: Philip Morris 2038 | D83: Philip Morris - 6.375% - May 2038 B-PM-6.375-16052038 | E83: 15000 | F83: USD | G83: 1000 | H83: 1112.83 | I83: 45977 | J83: 13.97 | K83: 1126.8 | L83: 956.85 | M83: 15.676438 | N83: 15 | O83: 16692.45 | P83: 14352.75 | Q83: High-carry defensive credit. Stable global tobacco cash flows support attractive income and portfolio yield stabilization. | R83: Philip Morris 6.375% May-2038 Investment Thesis Global tobacco with diversification vs Altria Lower regulatory concentration risk Role in Portfolio Complementary HY cash-flow exposure Sizing Logic $15k paired with Altria Expected Return Carry + credit stability Monitoring Reduced-risk product transition | S83: • Global diversification vs Altria • Strong cash flows • HY with lower regulatory concentration risk | T83: • Heated tobacco adoption • FX exposure • Credit metrics | U83: • Rebalance vs Altria if relative value shifts | V83: • Intra-sector relative value within tobacco
B84: Event / Cyclical HY (8% = €24,000) | C84: Boeing 2043 | D84: Boeing Co - 6.875% - Oct 2043 B-BA-6.875-15102043 | E84: 15000 | F84: USD | G84: 1000 | H84: 1080 | I84: 45945 | J84: 21.1 | K84: 1101.1 | L84: 943.51 | M84: 15.898083 | N84: 15 | O84: 16200 | P84: 14152.65 | Q84: Cyclical recovery credit with elevated carry. Position targets spread compression as Boeing normalizes operations and cash flow over the cycle. | R84: Boeing 2043 — €15,000（5%） Investment Thesis Event-driven high yield exposure linked to operational normalization and delivery recovery. Role in Portfolio Return enhancer with asymmetric upside from credit spread compression. Sizing Logic Capped at 5% due to idiosyncratic operational and regulatory risks. Expected Return Sources High coupon carry Spread tightening upon resolution of production and safety issues Key Risks & Mitigants Risk: New safety incidents or delivery halts Mitigant: Limited sizing and diversification across HY bucket Monitoring & Exit Triggers FAA approvals Aircraft delivery schedules Exit if operational setbacks re-emerge | S84: • Event-driven HY credit • Recovery upside from aerospace normalization • High carry compensation | T84: • Aircraft deliveries • Free cash flow • Rating outlook | U84: • Exit if recovery stalls • Trim after major credit upgrade | V84: • Event risk vs carry in cyclical credits
C85: US Steel 2029 | D85: United States Steel Corp - 6.875% - Mar 2029 B-X-6.875-01032029 | E85: 9000 | F85: USD | G85: 1000 | H85: 1004.57 | I85: 45901 | J85: 29.38 | K85: 1033.95 | L85: 878 | M85: 10.250569 | N85: 10 | O85: 10045.7 | P85: 8780 | Q85: Short-dated cyclical credit capturing high carry with limited duration risk. Trade targets stable income and near-term spread normalization into 2029 maturity. | R85: US Steel 6.875% Mar-2029 Investment Thesis Short-dated cyclical commodity credit High carry with limited duration risk Role in Portfolio Tactical HY cycle exposure Sizing Logic $9k small satellite position Expected Return Carry + pull-to-par Monitoring Steel prices, demand cycle | S85: • Late-cycle cyclical HY exposure • Shorter tenor limits downside • Commodity-linked rebound play | T85: • Steel prices • Global demand • Balance sheet discipline | U85: • Exit if cycle turns down • Hold to maturity if stable | V85: • Timing risk in commodity-linked credit
A86: Relative Value Strategies (20% = €60,000) | B86: Sovereign Spread Trade (10% = €30,000) | C86: BTP 2040 Long | D86: BTP 3.100% 03-Jan-2040 IT-B-3.100-03012040 | E86: 15000 | F86: EUR | G86: 1000 | H86: 925.86 | I86: 45901 | J86: 13.25 | K86: 939.11 | L86: 939.51 | M86: 15.965769 | N86: 15 | O86: 13887.9 | P86: 14092.65 | Q86: Long BTP 2040 to express ECB easing and Italy spread compression. High duration and clean rates/spread beta with manageable volatility over 2-month horizon. | R86: Long BTP 2040 — €15,000（5%） Investment Thesis Relative value trade expressing convergence between Italian sovereign spreads and core EUR rates under ECB backstop. Role in Portfolio Spread trade rather than pure duration exposure. Sizing Logic Matched against Bund hedge to isolate spread movement. Expected Return Sources BTP–Bund spread compression Carry advantage vs core sovereigns Key Risks & Mitigants Risk: Italian fiscal slippage or political shock Mitigant: Bund hedge neutralizes rate risk Monitoring & Exit Triggers BTP–Bund spread levels Italian budget announcements ECB transmission protection signals | S86: • Peripheral sovereign spread compression play • Long Italy duration • ECB backstop exposure | T86: • BTP–Bund spread • Italian fiscal policy • ECB support stance | U86: • Exit if political risk escalates • Take profit on spread tightening | V86: • Sovereign spread dynamics in EUR
C87: Bund 2040 Short | D87: BUND 4.750% 04-Jul-2040 DE-B-4.750-04072040 | E87: 15000 | F87: EUR | G87: 1000 | H87: 1184.56 | I87: 46026 | J87: 4.03 | K87: 1188.59 | L87: 1189.1 | M87: 12.614582 | N87: 12 | O87: 14214.72 | P87: 14269.2 | Q87: Short Bund 2040 as duration hedge against long BTP/OAT. Neutralizes pure rate risk while retaining peripheral spread compression exposure. | R87: Bund 4.750% Jul-2040 (Short / Hedge) Investment Thesis Hedge against EUR rate rise Neutralizes duration in BTP leg Role in Portfolio Relative-value hedge leg Sizing Logic €15k matched notional Expected Return Relative performance vs BTP Monitoring BTP-Bund spread dynamics | S87: • Hedge against BTP spread widening • Duration-neutral EUR RV trade • Risk-off protection leg | T87: • Bund yields • ECB communication • BTP volatility | U87: • Adjust hedge ratio if spreads compress materially | V87: • How sovereign hedges work in RV trades
B88: Credit Relative Value (10% = €30,000) | C88: JPM 2038 | D88: JP Morgan Chase Co - 6.400% - May 2038 B-JPM-6.4-15052038 | E88: 10000 | F88: USD | G88: 1000 | H88: 1152.58 | I88: 45976 | J88: 14.2 | K88: 1166.78 | L88: 990.8 | M88: 10.092854 | N88: 10 | O88: 11525.8 | P88: 9908 | Q88: Long JPM 6.4% May-2038 as a credit relative value anchor. High coupon provides strong carry while long maturity offers duration exposure. Position expresses bank credit stability with limited idiosyncratic risk and benefits from spread compression or long-end yield declines. | R88: JPM 6.400% May-2038 Investment Thesis High-quality US bank credit Attractive yield vs peers Role in Portfolio Credit relative-value anchor Sizing Logic $10k core financial credit Expected Return Carry + modest spread tightening Monitoring Capital ratios, macro credit cycle | S88: • Systemic bank credit • High coupon IG/HY crossover • Financials RV anchor | T88: • Bank funding spreads • Yield curve shape • Regulatory capital ratios | U88: • Trim if spreads normalize fully • Exit on financial stress | V88: • Bank credit sensitivity to macro cycles
C89: JPM 2040 | D89: JP Morgan Chase Co - 5.500% - Oct 2040 B-JPM-5.5-15102040 | E89: 8000 | F89: USD | G89: 1000 | H89: 1041.4 | I89: 45945 | J89: 16.88 | K89: 1058.28 | L89: 898.66 | M89: 8.9021432 | N89: 8 | O89: 8331.2 | P89: 7189.28 | Q89: Long JPM 5.5% Oct-2040 to extend bank credit duration with stable carry. Position targets long-end rate sensitivity and potential credit spread tightening while maintaining exposure to a high-quality global systemically important bank. | R89: JPM 5.500% Oct-2040 Investment Thesis Longer-duration extension of JPM credit Higher rate sensitivity Role in Portfolio Curve steepness exposure within issuer Sizing Logic $8k smaller size due to duration Expected Return Carry + curve-driven price gains Monitoring Long-end rates, bank regulation | S89: • Longer-duration financial credit • Curve & spread relative value vs JPM 2038 • Carry + duration mix | T89: • Long-end rates • Bank term funding costs • Credit curve slope | U89: • Switch to shorter tenor if curve steepens | V89: • Credit curve positioning within one issuer
C90: Sanofi 2038 | D90: Sanofi S.A - 1.875% - Mar 2038 FR-SNY-1.875-21032038 | E90: 7000 | F90: EUR | G90: 1000 | H90: 838.91 | I90: 45921 | J90: 6.99 | K90: 845.9 | L90: 849.84 | M90: 8.2368446 | N90: 8 | O90: 6711.28 | P90: 6798.72 | Q90: Non-financial IG anchor in Credit RV bucket. Defensive pharma cash flows with low beta. Used as spread benchmark versus bank credit to isolate financial sector-specific spread moves. | R90: Sanofi 1.875% Mar-2038 Investment Thesis Defensive healthcare IG Stable earnings and low cyclicality Role in Portfolio Non-tech IG diversifier Sizing Logic €7k satellite allocation Expected Return Duration + stability premium Monitoring Pipeline, regulatory updates | S90: • Defensive healthcare IG • Low business cyclicality • EUR duration diversifier | T90: • Drug pipeline updates • Litigation risk • EUR credit spreads | U90: • Trim if valuation richens • Exit on adverse clinical events | V90: • Stability of healthcare credit through cycles
C91: TotalEnergies 2039 | D91: TotalEnergies Capital Intl. - 1.535% - May 2039 FR-TTE-1.535-31052039 | E91: 5000 | F91: EUR | G91: 1000 | H91: 749.91 | I91: 45991 | J91: 2.78 | K91: 752.69 | L91: 755.78 | M91: 6.6156818 | N91: 6 | O91: 4499.46 | P91: 4534.68 | Q91: Non-financial IG energy credit added as macro-sensitive leg in Credit RV bucket. Provides diversification from tech and financials while linking portfolio to inflation and commodity dynamics. | R91: TotalEnergies 1.535% May-2039 Investment Thesis Integrated energy major with strong balance sheet Long-dated IG exposure Role in Portfolio Energy transition-linked IG credit Sizing Logic €5k small allocation due to low coupon Expected Return Rate-driven price appreciation Monitoring Energy prices, capex discipline | S91: • Energy major with strong FCF • Transition risk priced conservatively • Long-dated IG carry | T91: • Oil & gas prices • Energy transition capex • Credit leverage | U91: • Reduce if energy cycle peaks • Exit on leverage deterioration | V91: • Energy credit vs commodity volatility
A92: Tactical Cash (10% = €30,000) | E92: 30000 | R92: Tactical Cash — €30,000（10%） Investment Thesis Maintains optionality to exploit volatility-driven mispricings. Role in Portfolio Liquidity buffer and tactical deployment capital. Sizing Logic 10% ensures flexibility without diluting structural positions. Expected Return Sources Optionality rather than yield Monitoring & Exit Triggers Market stress events Forced selling in credit or rates markets | S92: Optionality & flexibility | U92: After CPI, Fed/ECB, spread shocks | V92: Liquidity as a portfolio tool
